[
 {
  "id": "tdnet-1192202",
  "date": "2025-09-17",
  "time": "18:00",
  "code": "278A",
  "name": "Ｇ－テラドローン",
  "exch": "東",
  "title": "（訂正）「2026年１月期　第２四半期（中間期）決算短信〔日本基準〕(連結)」の一部訂正について",
  "pdfUrl": "https://www.release.tdnet.info/inbs/140120250917559159.pdf",
  "src": "TDnet",
  "hasXbrl": false,
  "genre": "kessan",
  "tags": [
   "決算短信"
  ],
  "isCorrection": true,
  "market": "グロース"
 },
 {
  "id": "tdnet-1192197",
  "date": "2025-09-17",
  "time": "17:30",
  "code": "4464",
  "name": "ソフト９９",
  "exch": "東",
  "title": "（変更）「堯ＡＭ（株）による（株）ソフト９９コーポレーション（証券コード：4464）の株式に対する公開買付けの開始に関するお知らせ」の変更に関するお知らせ",
  "pdfUrl": "https://www.release.tdnet.info/inbs/140120250917559127.pdf",
  "src": "TDnet",
  "hasXbrl": false,
  "genre": "ma",
  "tags": [
   "公開買付け"
  ],
  "isCorrection": false,
  "market": "スタンダード"
 },
 {
  "id": "tdnet-1192196",
  "date": "2025-09-17",
  "time": "17:00",
  "code": "7719",
  "name": "東京衡機",
  "exch": "東",
  "title": "新中期経営計画の策定および業績予想の修正に関するお知らせ",
  "pdfUrl": "https://www.release.tdnet.info/inbs/140120250917558945.pdf",
  "src": "TDnet",
  "hasXbrl": true,
  "genre": "chukei",
  "tags": [
   "中期経営計画"
  ],
  "isCorrection": false,
  "market": "スタンダード"
 },
 {
  "id": "tdnet-1192190",
  "date": "2025-09-17",
  "time": "17:00",
  "code": "3070",
  "name": "Ｇ－ジェリービーンズ",
  "exch": "東",
  "title": "補足資料　株式会社 361Sports Japan の株式取得に関するお知らせ",
  "pdfUrl": "https://www.release.tdnet.info/inbs/140120250917559128.pdf",
  "src": "TDnet",
  "hasXbrl": false,
  "genre": "ma",
  "tags": [
   "株式取得"
  ],
  "isCorrection": false,
  "market": "グロース"
 },
 {
  "id": "tdnet-1192188",
  "date": "2025-09-17",
  "time": "17:00",
  "code": "1812",
  "name": "鹿島",
  "exch": "東",
  "title": "特定子会社の異動に関するお知らせ",
  "pdfUrl": "https://www.release.tdnet.info/inbs/140120250825546861.pdf",
  "src": "TDnet",
  "hasXbrl": false,
  "genre": "ma",
  "tags": [
   "子会社の異動"
  ],
  "isCorrection": false,
  "market": "プライム"
 },
 {
  "id": "tdnet-1192177",
  "date": "2025-09-17",
  "time": "16:00",
  "code": "9425",
  "name": "ＲｅＹｕｕＪａｐａｎ",
  "exch": "東",
  "title": "暗号資産の取扱開始の方針決定およびabc株式会社とのビットコインを活用したトレジャリー戦略に関する業務提携に向けた基本合意締結のお知らせ",
  "pdfUrl": "https://www.release.tdnet.info/inbs/140120250917558925.pdf",
  "src": "TDnet",
  "hasXbrl": false,
  "genre": "release",
  "tags": [
   "業務提携"
  ],
  "isCorrection": false,
  "market": "スタンダード"
 },
 {
  "id": "tdnet-1192118",
  "date": "2025-09-17",
  "time": "15:45",
  "code": "3471",
  "name": "Ｒ－三井不ロジパーク",
  "exch": "東",
  "title": "2025年7月期 決算短信（REIT）",
  "pdfUrl": "https://www.release.tdnet.info/inbs/140120250916558544.pdf",
  "src": "TDnet",
  "hasXbrl": true,
  "genre": "kessan",
  "tags": [
   "決算短信"
  ],
  "isCorrection": false,
  "market": "不明"
 },
 {
  "id": "tdnet-1192159",
  "date": "2025-09-17",
  "time": "15:30",
  "code": "9251",
  "name": "Ｇ－ＡＢ＆Ｃ",
  "exch": "東",
  "title": "株式会社SENSEの株式の取得（連結子会社化）に関するお知らせ",
  "pdfUrl": "https://www.release.tdnet.info/inbs/140120250917558761.pdf",
  "src": "TDnet",
  "hasXbrl": false,
  "genre": "ma",
  "tags": [
   "子会社化"
  ],
  "isCorrection": false,
  "market": "グロース"
 },
 {
  "id": "tdnet-1192156",
  "date": "2025-09-17",
  "time": "15:30",
  "code": "9226",
  "name": "Ｐ－アイガー",
  "exch": "東",
  "title": "（訂正）「2025年11月期  中間決算短信〔日本基準〕（連結）」の一部訂正について",
  "pdfUrl": "https://www.release.tdnet.info/inbs/140120250916558604.pdf",
  "src": "TDnet",
  "hasXbrl": false,
  "genre": "kessan",
  "tags": [
   "決算短信"
  ],
  "isCorrection": true,
  "market": "不明"
 },
 {
  "id": "tdnet-1192137",
  "date": "2025-09-17",
  "time": "15:30",
  "code": "6042",
  "name": "ニッキ",
  "exch": "東",
  "title": "大島機工株式会社の株式の取得（子会社化）に関するお知らせ",
  "pdfUrl": "https://www.release.tdnet.info/inbs/140120250916557935.pdf",
  "src": "TDnet",
  "hasXbrl": false,
  "genre": "ma",
  "tags": [
   "子会社化"
  ],
  "isCorrection": false,
  "market": "スタンダード"
 },
 {
  "id": "tdnet-1192134",
  "date": "2025-09-17",
  "time": "15:30",
  "code": "4840",
  "name": "Ｇ－トライアイズ",
  "exch": "東",
  "title": "（訂正）連結子会社の異動（株式売却）に関するお知らせ",
  "pdfUrl": "https://www.release.tdnet.info/inbs/140120250917559049.pdf",
  "src": "TDnet",
  "hasXbrl": false,
  "genre": "ma",
  "tags": [
   "子会社の異動"
  ],
  "isCorrection": true,
  "market": "スタンダード"
 },
 {
  "id": "tdnet-1192123",
  "date": "2025-09-17",
  "time": "15:30",
  "code": "3249",
  "name": "Ｒ－産業ファ",
  "exch": "東",
  "title": "2025年7月期　決算短信(REIT)",
  "pdfUrl": "https://www.release.tdnet.info/inbs/140120250917559030.pdf",
  "src": "TDnet",
  "hasXbrl": true,
  "genre": "kessan",
  "tags": [
   "決算短信"
  ],
  "isCorrection": false,
  "market": "不明"
 },
 {
  "id": "tdnet-1192115",
  "date": "2025-09-17",
  "time": "15:00",
  "code": "3341",
  "name": "日本調剤",
  "exch": "東",
  "title": "株式会社AP86による当社株式に対する公開買付けの結果並びに親会社、主要株主である筆頭株主、主要株主及び支配株主（親会社を除く。）の異動に関するお知らせ",
  "pdfUrl": "https://www.release.tdnet.info/inbs/140120250912557802.pdf",
  "src": "TDnet",
  "hasXbrl": false,
  "genre": "ma",
  "tags": [
   "公開買付け"
  ],
  "isCorrection": false,
  "market": "不明"
 },
 {
  "id": "tdnet-1192108",
  "date": "2025-09-17",
  "time": "14:00",
  "code": "9432",
  "name": "ＮＴＴ",
  "exch": "東",
  "title": "当社子会社（NTTドコモ）によるCARTA HOLDINGS株券等（証券コード：3688）に対する公開買付けの結果に関するお知らせ",
  "pdfUrl": "https://www.release.tdnet.info/inbs/140120250916557924.pdf",
  "src": "TDnet",
  "hasXbrl": false,
  "genre": "ma",
  "tags": [
   "公開買付け"
  ],
  "isCorrection": false,
  "market": "プライム"
 },
 {
  "id": "tdnet-1192107",
  "date": "2025-09-17",
  "time": "14:00",
  "code": "3688",
  "name": "ＣＡＲＴＡ　ＨＤ",
  "exch": "東",
  "title": "株式会社NTTドコモによる当社株券等に対する公開買付けの結果並びにその他の関係会社及び主要株主の異動に関するお知らせ",
  "pdfUrl": "https://www.release.tdnet.info/inbs/140120250917558644.pdf",
  "src": "TDnet",
  "hasXbrl": false,
  "genre": "ma",
  "tags": [
   "公開買付け"
  ],
  "isCorrection": false,
  "market": "不明"
 },
 {
  "id": "tdnet-1192101",
  "date": "2025-09-17",
  "time": "13:05",
  "code": "2117",
  "name": "ウェルネオシュガー",
  "exch": "東",
  "title": "自己株式取得に係る事項の決定に関するお知らせ（会社法第165条第2項の規定による定款の定めに基づく自己株式の取得）",
  "pdfUrl": "https://www.release.tdnet.info/inbs/140120250916558606.pdf",
  "src": "TDnet",
  "hasXbrl": false,
  "genre": "ma",
  "tags": [
   "株式取得"
  ],
  "isCorrection": false,
  "market": "プライム"
 },
 {
  "id": "tdnet-1192099",
  "date": "2025-09-17",
  "time": "12:30",
  "code": "3777",
  "name": "Ｇ－環境フレンドリー",
  "exch": "東",
  "title": "（開示事項の経過）杭州衆能光電科技有限公司との業務提携契約締結のお知らせ",
  "pdfUrl": "https://www.release.tdnet.info/inbs/140120250917558771.pdf",
  "src": "TDnet",
  "hasXbrl": false,
  "genre": "release",
  "tags": [
   "業務提携"
  ],
  "isCorrection": false,
  "market": "グロース"
 },
 {
  "id": "tdnet-1192098",
  "date": "2025-09-17",
  "time": "12:30",
  "code": "3358",
  "name": "ワイエスフード",
  "exch": "東",
  "title": "ミシュランシェフ 西村貴仁氏との業務提携およびCCO就任のお知らせ",
  "pdfUrl": "https://www.release.tdnet.info/inbs/140120250917558905.pdf",
  "src": "TDnet",
  "hasXbrl": false,
  "genre": "release",
  "tags": [
   "業務提携"
  ],
  "isCorrection": false,
  "market": "スタンダード"
 },
 {
  "id": "tdnet-1192079",
  "date": "2025-09-17",
  "time": "09:00",
  "code": "3282",
  "name": "Ｒ－コンフォリア",
  "exch": "東",
  "title": "（訂正）「2025年７月期 決算短信（ＲＥＩＴ）」の一部訂正に関するお知らせ",
  "pdfUrl": "https://www.release.tdnet.info/inbs/140120250916558636.pdf",
  "src": "TDnet",
  "hasXbrl": false,
  "genre": "kessan",
  "tags": [
   "決算短信"
  ],
  "isCorrection": true,
  "market": "不明"
 }
]
