[
 {
  "id": "tdnet-1196162",
  "date": "2025-10-14",
  "time": "18:45",
  "code": "7085",
  "name": "株式会社カーブスホールディングス",
  "exch": "東",
  "title": "2025年８月期 決算短信〔日本基準〕(連結)",
  "pdfUrl": "https://www.release.tdnet.info/inbs/140120251014572674.pdf",
  "src": "TDnet",
  "hasXbrl": true,
  "genre": "kessan",
  "tags": [
   "決算短信"
  ],
  "isCorrection": false,
  "market": "プライム"
 },
 {
  "id": "tdnet-1196159",
  "date": "2025-10-14",
  "time": "18:30",
  "code": "2901",
  "name": "株式会社ウェルディッシュ",
  "exch": "東",
  "title": "株式会社IMGホールディングスの株式交換による完全子会社化に関するお知らせ",
  "pdfUrl": "https://www.release.tdnet.info/inbs/140120251014573361.pdf",
  "src": "TDnet",
  "hasXbrl": false,
  "genre": "ma",
  "tags": [
   "子会社化",
   "株式交換"
  ],
  "isCorrection": false,
  "market": "スタンダード"
 },
 {
  "id": "tdnet-1196158",
  "date": "2025-10-14",
  "time": "18:30",
  "code": "2901",
  "name": "株式会社ウェルディッシュ",
  "exch": "東",
  "title": "2025年8月期　決算短信［日本基準］（連結）",
  "pdfUrl": "https://www.release.tdnet.info/inbs/140120251014573332.pdf",
  "src": "TDnet",
  "hasXbrl": true,
  "genre": "kessan",
  "tags": [
   "決算短信"
  ],
  "isCorrection": false,
  "market": "スタンダード"
 },
 {
  "id": "tdnet-1196153",
  "date": "2025-10-14",
  "time": "18:01",
  "code": "2901",
  "name": "株式会社ウェルディッシュ",
  "exch": "東",
  "title": "(訂正・数値データ訂正)「2025年8月期　第1四半期決算短信［日本基準］（連結）」の一部訂正に関するお知らせ",
  "pdfUrl": "https://www.release.tdnet.info/inbs/140120251014573328.pdf",
  "src": "TDnet",
  "hasXbrl": true,
  "genre": "kessan",
  "tags": [
   "決算短信"
  ],
  "isCorrection": true,
  "market": "スタンダード"
 },
 {
  "id": "tdnet-1196154",
  "date": "2025-10-14",
  "time": "18:00",
  "code": "6312",
  "name": "フロイント",
  "exch": "東",
  "title": "(訂正)公開買付届出書の訂正届出書の提出に伴う「(株)友によるフロイント産業(株)の株式に対する公開買付けの開始に関するお知らせ」の一部訂正に関するお知らせ",
  "pdfUrl": "https://www.release.tdnet.info/inbs/140120251014573149.pdf",
  "src": "TDnet",
  "hasXbrl": false,
  "genre": "ma",
  "tags": [
   "公開買付け"
  ],
  "isCorrection": true,
  "market": "不明"
 },
 {
  "id": "tdnet-1196151",
  "date": "2025-10-14",
  "time": "17:30",
  "code": "7837",
  "name": "株式会社アールシーコア",
  "exch": "東",
  "title": "旭化成ホームズ株式会社との資本業務提携契約の締結並びに主要株主及び主要株主である筆頭株主の異動に関するお知らせ",
  "pdfUrl": "https://www.release.tdnet.info/inbs/140120251009571205.pdf",
  "src": "TDnet",
  "hasXbrl": false,
  "genre": "ma",
  "tags": [
   "資本業務提携"
  ],
  "isCorrection": false,
  "market": "スタンダード"
 },
 {
  "id": "tdnet-1196149",
  "date": "2025-10-14",
  "time": "17:30",
  "code": "7523",
  "name": "アールビバン株式会社",
  "exch": "東",
  "title": "(訂正)公開買付届出書の訂正届出書の提出に伴う「(株)Orsayによるアールビバン(株)株式に対する公開買付けの開始に関するお知らせ」の一部訂正に関するお知らせ",
  "pdfUrl": "https://www.release.tdnet.info/inbs/140120251014573294.pdf",
  "src": "TDnet",
  "hasXbrl": false,
  "genre": "ma",
  "tags": [
   "公開買付け"
  ],
  "isCorrection": true,
  "market": "スタンダード"
 },
 {
  "id": "tdnet-1196148",
  "date": "2025-10-14",
  "time": "17:30",
  "code": "3407",
  "name": "旭化成株式会社",
  "exch": "東",
  "title": "旭化成ホームズ株式会社による株式会社アールシーコア（証券コード：7837）株式の買集め行為に該当する株式取得についてのお知らせ",
  "pdfUrl": "https://www.release.tdnet.info/inbs/140120251014572865.pdf",
  "src": "TDnet",
  "hasXbrl": false,
  "genre": "ma",
  "tags": [
   "株式取得"
  ],
  "isCorrection": false,
  "market": "プライム"
 },
 {
  "id": "tdnet-1196147",
  "date": "2025-10-14",
  "time": "17:30",
  "code": "2164",
  "name": "株式会社地域新聞社",
  "exch": "東",
  "title": "株式会社アクティブ アンド カンパニーとの資本業務提携及び「奨学金返済支援型」人材紹介事業開始に関するお知らせ",
  "pdfUrl": "https://www.release.tdnet.info/inbs/140120251014573284.pdf",
  "src": "TDnet",
  "hasXbrl": false,
  "genre": "ma",
  "tags": [
   "資本業務提携"
  ],
  "isCorrection": false,
  "market": "スタンダード"
 },
 {
  "id": "tdnet-1196135",
  "date": "2025-10-14",
  "time": "17:00",
  "code": "8289",
  "name": "株式会社Ｏｌｙｍｐｉｃグループ",
  "exch": "東",
  "title": "2026年２月期第２四半期(中間期)決算短信[日本基準](連結)",
  "pdfUrl": "https://www.release.tdnet.info/inbs/140120251014572615.pdf",
  "src": "TDnet",
  "hasXbrl": true,
  "genre": "kessan",
  "tags": [
   "決算短信"
  ],
  "isCorrection": false,
  "market": "不明"
 },
 {
  "id": "tdnet-1196134",
  "date": "2025-10-14",
  "time": "17:00",
  "code": "7790",
  "name": "株式会社バルコス",
  "exch": "名",
  "title": "株式会社藤本コーポレーションの株式の取得（子会社化）に関するお知らせ",
  "pdfUrl": "https://www.release.tdnet.info/inbs/140120251014573228.pdf",
  "src": "TDnet",
  "hasXbrl": false,
  "genre": "ma",
  "tags": [
   "子会社化"
  ],
  "isCorrection": false,
  "market": "地方"
 },
 {
  "id": "tdnet-1196129",
  "date": "2025-10-14",
  "time": "17:00",
  "code": "4920",
  "name": "株式会社日本色材工業研究所",
  "exch": "東",
  "title": "2026年2月期 第2四半期（中間期）決算短信〔日本基準〕（連結）",
  "pdfUrl": "https://www.release.tdnet.info/inbs/140120251002567795.pdf",
  "src": "TDnet",
  "hasXbrl": true,
  "genre": "kessan",
  "tags": [
   "決算短信"
  ],
  "isCorrection": false,
  "market": "スタンダード"
 },
 {
  "id": "tdnet-1196123",
  "date": "2025-10-14",
  "time": "17:00",
  "code": "3083",
  "name": "スターシーズ株式会社",
  "exch": "東",
  "title": "2026年２月期 第２四半期（中間期）決算短信〔日本基準〕（連結）",
  "pdfUrl": "https://www.release.tdnet.info/inbs/140120251014573114.pdf",
  "src": "TDnet",
  "hasXbrl": true,
  "genre": "kessan",
  "tags": [
   "決算短信"
  ],
  "isCorrection": false,
  "market": "スタンダード"
 },
 {
  "id": "tdnet-1196121",
  "date": "2025-10-14",
  "time": "17:00",
  "code": "293A",
  "name": "Ｐ－ＢＡＢＹ　ＪＯＢ",
  "exch": "東",
  "title": "2026年２月期 第２四半期（中間期）決算短信〔日本基準〕（連結）",
  "pdfUrl": "https://www.release.tdnet.info/inbs/140120251014572569.pdf",
  "src": "TDnet",
  "hasXbrl": false,
  "genre": "kessan",
  "tags": [
   "決算短信"
  ],
  "isCorrection": false,
  "market": "不明"
 },
 {
  "id": "tdnet-1196119",
  "date": "2025-10-14",
  "time": "17:00",
  "code": "139A",
  "name": "Ｐ－東日本地所",
  "exch": "東",
  "title": "（訂正）「2025年8月期 決算短信〔日本基準〕（連結）」の一部訂正について",
  "pdfUrl": "https://www.release.tdnet.info/inbs/140120251014573015.pdf",
  "src": "TDnet",
  "hasXbrl": false,
  "genre": "kessan",
  "tags": [
   "決算短信"
  ],
  "isCorrection": true,
  "market": "不明"
 },
 {
  "id": "tdnet-1196143",
  "date": "2025-10-14",
  "time": "16:45",
  "code": "6334",
  "name": "明治機械株式会社",
  "exch": "東",
  "title": "京都製麦研究開発株式会社との業務提携に関するお知らせ",
  "pdfUrl": "https://www.release.tdnet.info/inbs/140120251008570422.pdf",
  "src": "TDnet",
  "hasXbrl": false,
  "genre": "release",
  "tags": [
   "業務提携"
  ],
  "isCorrection": false,
  "market": "スタンダード"
 },
 {
  "id": "tdnet-1196140",
  "date": "2025-10-14",
  "time": "16:45",
  "code": "3647",
  "name": "株式会社ジー・スリーホールディングス",
  "exch": "東",
  "title": "2025年８月期決算短信〔日本基準〕（連結）",
  "pdfUrl": "https://www.release.tdnet.info/inbs/140120251014573173.pdf",
  "src": "TDnet",
  "hasXbrl": true,
  "genre": "kessan",
  "tags": [
   "決算短信"
  ],
  "isCorrection": false,
  "market": "スタンダード"
 },
 {
  "id": "tdnet-1196137",
  "date": "2025-10-14",
  "time": "16:45",
  "code": "144A",
  "name": "Ｐ－エネルギーパワー",
  "exch": "東",
  "title": "2025年８月期　決算短信〔日本基準〕（非連結）",
  "pdfUrl": "https://www.release.tdnet.info/inbs/140120251014572812.pdf",
  "src": "TDnet",
  "hasXbrl": false,
  "genre": "kessan",
  "tags": [
   "決算短信"
  ],
  "isCorrection": false,
  "market": "不明"
 },
 {
  "id": "tdnet-1196116",
  "date": "2025-10-14",
  "time": "16:30",
  "code": "7685",
  "name": "株式会社ＢｕｙＳｅｌｌ　Ｔｅｃｈｎｏｌｏｇｉｅｓ",
  "exch": "東",
  "title": "完全子会社及び完全孫会社間の吸収合併並びに当社及び完全子会社間の吸収合併に関するお知らせ",
  "pdfUrl": "https://www.release.tdnet.info/inbs/140120251014572833.pdf",
  "src": "TDnet",
  "hasXbrl": false,
  "genre": "ma",
  "tags": [
   "吸収合併"
  ],
  "isCorrection": false,
  "market": "グロース"
 },
 {
  "id": "tdnet-1196115",
  "date": "2025-10-14",
  "time": "16:30",
  "code": "7255",
  "name": "株式会社　桜井製作所",
  "exch": "東",
  "title": "自己株式取得に係る事項の決定に関するお知らせ",
  "pdfUrl": "https://www.release.tdnet.info/inbs/140120251014573083.pdf",
  "src": "TDnet",
  "hasXbrl": false,
  "genre": "ma",
  "tags": [
   "株式取得"
  ],
  "isCorrection": false,
  "market": "スタンダード"
 },
 {
  "id": "tdnet-1196111",
  "date": "2025-10-14",
  "time": "16:30",
  "code": "4668",
  "name": "株式会社明光ネットワークジャパン",
  "exch": "東",
  "title": "2025年８月期通期連結業績予想と実績値との差異および中期経営計画（2025年８月期-2027年８月期）における経営指標（計画）の修正に関するお知らせ",
  "pdfUrl": "https://www.release.tdnet.info/inbs/140120251010572060.pdf",
  "src": "TDnet",
  "hasXbrl": false,
  "genre": "chukei",
  "tags": [
   "中期経営計画"
  ],
  "isCorrection": false,
  "market": "プライム"
 },
 {
  "id": "tdnet-1196109",
  "date": "2025-10-14",
  "time": "16:30",
  "code": "4668",
  "name": "株式会社明光ネットワークジャパン",
  "exch": "東",
  "title": "2025年８月期決算短信〔日本基準〕（連結）",
  "pdfUrl": "https://www.release.tdnet.info/inbs/140120251010572142.pdf",
  "src": "TDnet",
  "hasXbrl": true,
  "genre": "kessan",
  "tags": [
   "決算短信"
  ],
  "isCorrection": false,
  "market": "プライム"
 },
 {
  "id": "tdnet-1196106",
  "date": "2025-10-14",
  "time": "16:30",
  "code": "4176",
  "name": "株式会社ココナラ",
  "exch": "東",
  "title": "2025年８月期 決算短信〔日本基準〕（連結）",
  "pdfUrl": "https://www.release.tdnet.info/inbs/140120251014573235.pdf",
  "src": "TDnet",
  "hasXbrl": true,
  "genre": "kessan",
  "tags": [
   "決算短信"
  ],
  "isCorrection": false,
  "market": "グロース"
 },
 {
  "id": "tdnet-1196099",
  "date": "2025-10-14",
  "time": "16:30",
  "code": "3387",
  "name": "株式会社クリエイト・レストランツ・ホールディングス",
  "exch": "東",
  "title": "2026年２月期第２四半期（中間期）決算短信〔ＩＦＲＳ〕（連結）",
  "pdfUrl": "https://www.release.tdnet.info/inbs/140120251010571656.pdf",
  "src": "TDnet",
  "hasXbrl": true,
  "genre": "kessan",
  "tags": [
   "決算短信"
  ],
  "isCorrection": false,
  "market": "プライム"
 },
 {
  "id": "tdnet-1196097",
  "date": "2025-10-14",
  "time": "16:30",
  "code": "3269",
  "name": "Ｒ－ＡＤＲ",
  "exch": "東",
  "title": "（訂正）「2025年7月期　決算短信（REIT）」の一部訂正に関するお知らせ",
  "pdfUrl": "https://www.release.tdnet.info/inbs/140120251014573140.pdf",
  "src": "TDnet",
  "hasXbrl": false,
  "genre": "kessan",
  "tags": [
   "決算短信"
  ],
  "isCorrection": true,
  "market": "不明"
 },
 {
  "id": "tdnet-1196094",
  "date": "2025-10-14",
  "time": "16:30",
  "code": "2736",
  "name": "フェスタリアホールディングス株式会社",
  "exch": "東",
  "title": "2025年８月期　決算短信〔日本基準〕(連結)",
  "pdfUrl": "https://www.release.tdnet.info/inbs/140120251014573163.pdf",
  "src": "TDnet",
  "hasXbrl": true,
  "genre": "kessan",
  "tags": [
   "決算短信"
  ],
  "isCorrection": false,
  "market": "スタンダード"
 },
 {
  "id": "tdnet-1196090",
  "date": "2025-10-14",
  "time": "16:00",
  "code": "9979",
  "name": "株式会社大庄",
  "exch": "東",
  "title": "2025年8月期決算短信〔日本基準〕（連結）",
  "pdfUrl": "https://www.release.tdnet.info/inbs/140120251014572594.pdf",
  "src": "TDnet",
  "hasXbrl": true,
  "genre": "kessan",
  "tags": [
   "決算短信"
  ],
  "isCorrection": false,
  "market": "スタンダード"
 },
 {
  "id": "tdnet-1196087",
  "date": "2025-10-14",
  "time": "16:00",
  "code": "9418",
  "name": "株式会社Ｕ－ＮＥＸＴ　ＨＯＬＤＩＮＧＳ",
  "exch": "東",
  "title": "中期経営計画の策定に関するお知らせ",
  "pdfUrl": "https://www.release.tdnet.info/inbs/140120251014572506.pdf",
  "src": "TDnet",
  "hasXbrl": false,
  "genre": "chukei",
  "tags": [
   "中期経営計画"
  ],
  "isCorrection": false,
  "market": "プライム"
 },
 {
  "id": "tdnet-1196084",
  "date": "2025-10-14",
  "time": "16:00",
  "code": "9418",
  "name": "株式会社Ｕ－ＮＥＸＴ　ＨＯＬＤＩＮＧＳ",
  "exch": "東",
  "title": "2025年８月期決算短信［日本基準］（連結）",
  "pdfUrl": "https://www.release.tdnet.info/inbs/140120251014572451.pdf",
  "src": "TDnet",
  "hasXbrl": true,
  "genre": "kessan",
  "tags": [
   "決算短信"
  ],
  "isCorrection": false,
  "market": "プライム"
 },
 {
  "id": "tdnet-1196083",
  "date": "2025-10-14",
  "time": "16:00",
  "code": "9326",
  "name": "関通ホールディングス株式会社",
  "exch": "東",
  "title": "持株会社体制への移行に係る会社分割の一部見直し(準備会社の追加設立)について",
  "pdfUrl": "https://www.release.tdnet.info/inbs/140120251014572565.pdf",
  "src": "TDnet",
  "hasXbrl": false,
  "genre": "ma",
  "tags": [
   "会社分割"
  ],
  "isCorrection": false,
  "market": "グロース"
 },
 {
  "id": "tdnet-1196082",
  "date": "2025-10-14",
  "time": "16:00",
  "code": "9326",
  "name": "関通ホールディングス株式会社",
  "exch": "東",
  "title": "2026年２月期 第２四半期（中間期）決算短信〔日本基準〕（連結）",
  "pdfUrl": "https://www.release.tdnet.info/inbs/140120251014572535.pdf",
  "src": "TDnet",
  "hasXbrl": true,
  "genre": "kessan",
  "tags": [
   "決算短信"
  ],
  "isCorrection": false,
  "market": "グロース"
 },
 {
  "id": "tdnet-1196081",
  "date": "2025-10-14",
  "time": "16:00",
  "code": "9256",
  "name": "株式会社サクシード",
  "exch": "東",
  "title": "（開示事項の経過）株式会社unicoの株式の取得による子会社化に関するお知らせ",
  "pdfUrl": "https://www.release.tdnet.info/inbs/140120251014573152.pdf",
  "src": "TDnet",
  "hasXbrl": false,
  "genre": "ma",
  "tags": [
   "子会社化"
  ],
  "isCorrection": false,
  "market": "グロース"
 },
 {
  "id": "tdnet-1196079",
  "date": "2025-10-14",
  "time": "16:00",
  "code": "8267",
  "name": "イオン株式会社",
  "exch": "東",
  "title": "2026年２月期　第2四半期決算短信〔日本基準〕（連結）",
  "pdfUrl": "https://www.release.tdnet.info/inbs/140120251010571302.pdf",
  "src": "TDnet",
  "hasXbrl": true,
  "genre": "kessan",
  "tags": [
   "決算短信"
  ],
  "isCorrection": false,
  "market": "プライム"
 },
 {
  "id": "tdnet-1196077",
  "date": "2025-10-14",
  "time": "16:00",
  "code": "8143",
  "name": "株式会社ラピーヌ",
  "exch": "東",
  "title": "2026年２月期　第２四半期（中間期）決算短信［日本基準］（連結）",
  "pdfUrl": "https://www.release.tdnet.info/inbs/140120250926563366.pdf",
  "src": "TDnet",
  "hasXbrl": true,
  "genre": "kessan",
  "tags": [
   "決算短信"
  ],
  "isCorrection": false,
  "market": "スタンダード"
 },
 {
  "id": "tdnet-1196074",
  "date": "2025-10-14",
  "time": "16:00",
  "code": "7607",
  "name": "株式会社進和",
  "exch": "東",
  "title": "2025年８月期決算短信〔日本基準〕(連結)",
  "pdfUrl": "https://www.release.tdnet.info/inbs/140120251014572747.pdf",
  "src": "TDnet",
  "hasXbrl": true,
  "genre": "kessan",
  "tags": [
   "決算短信"
  ],
  "isCorrection": false,
  "market": "プライム"
 },
 {
  "id": "tdnet-1196072",
  "date": "2025-10-14",
  "time": "16:00",
  "code": "7607",
  "name": "株式会社進和",
  "exch": "東",
  "title": "中期経営計画の修正に関するお知らせ",
  "pdfUrl": "https://www.release.tdnet.info/inbs/140120251014572794.pdf",
  "src": "TDnet",
  "hasXbrl": false,
  "genre": "chukei",
  "tags": [
   "中期経営計画"
  ],
  "isCorrection": false,
  "market": "プライム"
 },
 {
  "id": "tdnet-1196067",
  "date": "2025-10-14",
  "time": "16:00",
  "code": "6025",
  "name": "日本ＰＣサービス株式会社",
  "exch": "名",
  "title": "2025年８月期 決算短信〔日本基準〕（連結）",
  "pdfUrl": "https://www.release.tdnet.info/inbs/140120251010572187.pdf",
  "src": "TDnet",
  "hasXbrl": true,
  "genre": "kessan",
  "tags": [
   "決算短信"
  ],
  "isCorrection": false,
  "market": "地方"
 },
 {
  "id": "tdnet-1196062",
  "date": "2025-10-14",
  "time": "16:00",
  "code": "5578",
  "name": "ＡＲアドバンストテクノロジ株式会社",
  "exch": "東",
  "title": "2025年８月期 決算短信〔日本基準〕（連結）",
  "pdfUrl": "https://www.release.tdnet.info/inbs/140120251014572936.pdf",
  "src": "TDnet",
  "hasXbrl": true,
  "genre": "kessan",
  "tags": [
   "決算短信"
  ],
  "isCorrection": false,
  "market": "グロース"
 },
 {
  "id": "tdnet-1196057",
  "date": "2025-10-14",
  "time": "16:00",
  "code": "5527",
  "name": "株式会社ｐｒｏｐｅｒｔｙ　ｔｅｃｈｎｏｌｏｇｉｅｓ",
  "exch": "東",
  "title": "2025年11月期第３四半期決算短信〔日本基準〕(連結)",
  "pdfUrl": "https://www.release.tdnet.info/inbs/140120251014572574.pdf",
  "src": "TDnet",
  "hasXbrl": true,
  "genre": "kessan",
  "tags": [
   "決算短信"
  ],
  "isCorrection": false,
  "market": "グロース"
 },
 {
  "id": "tdnet-1196055",
  "date": "2025-10-14",
  "time": "16:00",
  "code": "5246",
  "name": "株式会社ＥＬＥＭＥＮＴＳ",
  "exch": "東",
  "title": "連結範囲の変更（連結子会社化）に関するお知らせ",
  "pdfUrl": "https://www.release.tdnet.info/inbs/140120251010572217.pdf",
  "src": "TDnet",
  "hasXbrl": false,
  "genre": "ma",
  "tags": [
   "子会社化"
  ],
  "isCorrection": false,
  "market": "グロース"
 },
 {
  "id": "tdnet-1196052",
  "date": "2025-10-14",
  "time": "16:00",
  "code": "5246",
  "name": "株式会社ＥＬＥＭＥＮＴＳ",
  "exch": "東",
  "title": "2025年11月期　第３四半期決算短信〔日本基準〕(連結)",
  "pdfUrl": "https://www.release.tdnet.info/inbs/140120251009570925.pdf",
  "src": "TDnet",
  "hasXbrl": true,
  "genre": "kessan",
  "tags": [
   "決算短信"
  ],
  "isCorrection": false,
  "market": "グロース"
 },
 {
  "id": "tdnet-1196051",
  "date": "2025-10-14",
  "time": "16:00",
  "code": "5018",
  "name": "株式会社ＭＯＲＥＳＣＯ",
  "exch": "東",
  "title": "2026年２月期第２四半期（中間期）決算短信〔日本基準〕(連結)",
  "pdfUrl": "https://www.release.tdnet.info/inbs/140120251008570155.pdf",
  "src": "TDnet",
  "hasXbrl": true,
  "genre": "kessan",
  "tags": [
   "決算短信"
  ],
  "isCorrection": false,
  "market": "スタンダード"
 },
 {
  "id": "tdnet-1196046",
  "date": "2025-10-14",
  "time": "16:00",
  "code": "4745",
  "name": "東京個別",
  "exch": "東",
  "title": "2026年２月期第２四半期（中間期）決算短信〔日本基準〕(連結)",
  "pdfUrl": "https://www.release.tdnet.info/inbs/140120251014572783.pdf",
  "src": "TDnet",
  "hasXbrl": true,
  "genre": "kessan",
  "tags": [
   "決算短信"
  ],
  "isCorrection": false,
  "market": "不明"
 },
 {
  "id": "tdnet-1196044",
  "date": "2025-10-14",
  "time": "16:00",
  "code": "4429",
  "name": "リックソフト株式会社",
  "exch": "東",
  "title": "2026年２月期第２四半期（中間期）決算短信〔日本基準〕(連結)",
  "pdfUrl": "https://www.release.tdnet.info/inbs/140120251010571759.pdf",
  "src": "TDnet",
  "hasXbrl": true,
  "genre": "kessan",
  "tags": [
   "決算短信"
  ],
  "isCorrection": false,
  "market": "グロース"
 },
 {
  "id": "tdnet-1196042",
  "date": "2025-10-14",
  "time": "16:00",
  "code": "4413",
  "name": "株式会社ボードルア",
  "exch": "東",
  "title": "2026年２月期第２四半期（中間期）　決算短信〔ＩＦＲＳ〕(連結)",
  "pdfUrl": "https://www.release.tdnet.info/inbs/140120251014572947.pdf",
  "src": "TDnet",
  "hasXbrl": true,
  "genre": "kessan",
  "tags": [
   "決算短信"
  ],
  "isCorrection": false,
  "market": "プライム"
 },
 {
  "id": "tdnet-1196041",
  "date": "2025-10-14",
  "time": "16:00",
  "code": "4197",
  "name": "株式会社アスマーク",
  "exch": "東",
  "title": "2025年11月期第３四半期決算短信〔日本基準〕（連結）",
  "pdfUrl": "https://www.release.tdnet.info/inbs/140120251014572488.pdf",
  "src": "TDnet",
  "hasXbrl": true,
  "genre": "kessan",
  "tags": [
   "決算短信"
  ],
  "isCorrection": false,
  "market": "スタンダード"
 },
 {
  "id": "tdnet-1196038",
  "date": "2025-10-14",
  "time": "16:00",
  "code": "3967",
  "name": "株式会社エルテス",
  "exch": "東",
  "title": "2026年２月期 第２四半期（中間期）決算短信〔日本基準〕(連結)",
  "pdfUrl": "https://www.release.tdnet.info/inbs/140120251010572093.pdf",
  "src": "TDnet",
  "hasXbrl": true,
  "genre": "kessan",
  "tags": [
   "決算短信"
  ],
  "isCorrection": false,
  "market": "グロース"
 },
 {
  "id": "tdnet-1196036",
  "date": "2025-10-14",
  "time": "16:00",
  "code": "3835",
  "name": "ｅＢＡＳＥ株式会社",
  "exch": "東",
  "title": "自己株式取得に係る事項の決定に関するお知らせ",
  "pdfUrl": "https://www.release.tdnet.info/inbs/140120251010571591.pdf",
  "src": "TDnet",
  "hasXbrl": false,
  "genre": "ma",
  "tags": [
   "株式取得"
  ],
  "isCorrection": false,
  "market": "プライム"
 },
 {
  "id": "tdnet-1196029",
  "date": "2025-10-14",
  "time": "16:00",
  "code": "3080",
  "name": "株式会社ジェーソン",
  "exch": "東",
  "title": "2026年２月期　第２四半期（中間期）決算短信〔日本基準〕（連結）",
  "pdfUrl": "https://www.release.tdnet.info/inbs/140120251001566520.pdf",
  "src": "TDnet",
  "hasXbrl": true,
  "genre": "kessan",
  "tags": [
   "決算短信"
  ],
  "isCorrection": false,
  "market": "スタンダード"
 },
 {
  "id": "tdnet-1196028",
  "date": "2025-10-14",
  "time": "16:00",
  "code": "3030",
  "name": "株式会社ハブ",
  "exch": "東",
  "title": "2026年２月期第２四半期（中間期）決算短信〔日本基準〕(非連結)",
  "pdfUrl": "https://www.release.tdnet.info/inbs/140120251014572584.pdf",
  "src": "TDnet",
  "hasXbrl": true,
  "genre": "kessan",
  "tags": [
   "決算短信"
  ],
  "isCorrection": false,
  "market": "スタンダード"
 },
 {
  "id": "tdnet-1196025",
  "date": "2025-10-14",
  "time": "16:00",
  "code": "2872",
  "name": "株式会社セイヒョー",
  "exch": "東",
  "title": "2026年２月期　第２四半期（中間期）決算短信〔日本基準〕（非連結）",
  "pdfUrl": "https://www.release.tdnet.info/inbs/140120251014572351.pdf",
  "src": "TDnet",
  "hasXbrl": true,
  "genre": "kessan",
  "tags": [
   "決算短信"
  ],
  "isCorrection": false,
  "market": "スタンダード"
 },
 {
  "id": "tdnet-1196024",
  "date": "2025-10-14",
  "time": "16:00",
  "code": "280A",
  "name": "株式会社ＴＭＨ",
  "exch": "東",
  "title": "2025年11月期  第３四半期決算短信〔日本基準〕（連結）",
  "pdfUrl": "https://www.release.tdnet.info/inbs/140120251009571239.pdf",
  "src": "TDnet",
  "hasXbrl": true,
  "genre": "kessan",
  "tags": [
   "決算短信"
  ],
  "isCorrection": false,
  "market": "グロース"
 },
 {
  "id": "tdnet-1196020",
  "date": "2025-10-14",
  "time": "16:00",
  "code": "2798",
  "name": "株式会社ワイズテーブルコーポレーション",
  "exch": "東",
  "title": "2026年2月期 第2四半期（中間期）決算短信〔日本基準〕（連結）",
  "pdfUrl": "https://www.release.tdnet.info/inbs/140120250922561019.pdf",
  "src": "TDnet",
  "hasXbrl": true,
  "genre": "kessan",
  "tags": [
   "決算短信"
  ],
  "isCorrection": false,
  "market": "スタンダード"
 },
 {
  "id": "tdnet-1196018",
  "date": "2025-10-14",
  "time": "16:00",
  "code": "2502",
  "name": "アサヒグループホールディングス株式会社",
  "exch": "東",
  "title": "サイバー攻撃によるシステム障害発生に伴う2025年12月期第3四半期決算短信の開示が四半期末後 45 日を超えることに関するお知らせ",
  "pdfUrl": "https://www.release.tdnet.info/inbs/140120251014572856.pdf",
  "src": "TDnet",
  "hasXbrl": false,
  "genre": "kessan",
  "tags": [
   "決算短信"
  ],
  "isCorrection": false,
  "market": "プライム"
 },
 {
  "id": "tdnet-1196017",
  "date": "2025-10-14",
  "time": "16:00",
  "code": "2001",
  "name": "株式会社ニップン",
  "exch": "東",
  "title": "自己株式取得に係る事項の決定に関するお知らせ",
  "pdfUrl": "https://www.release.tdnet.info/inbs/140120251014572577.pdf",
  "src": "TDnet",
  "hasXbrl": false,
  "genre": "ma",
  "tags": [
   "株式取得"
  ],
  "isCorrection": false,
  "market": "プライム"
 },
 {
  "id": "tdnet-1196016",
  "date": "2025-10-14",
  "time": "16:00",
  "code": "2001",
  "name": "株式会社ニップン",
  "exch": "東",
  "title": "2026年３月期 第１四半期決算短信〔日本基準〕（連結）（公認会計士等による期中レビューの完了）",
  "pdfUrl": "https://www.release.tdnet.info/inbs/140120251014572513.pdf",
  "src": "TDnet",
  "hasXbrl": true,
  "genre": "kessan",
  "tags": [
   "決算短信"
  ],
  "isCorrection": false,
  "market": "プライム"
 },
 {
  "id": "tdnet-1196012",
  "date": "2025-10-14",
  "time": "16:00",
  "code": "189A",
  "name": "株式会社Ｄ＆Ｍカンパニー",
  "exch": "東",
  "title": "2026年５月期第１四半期決算短信〔日本基準〕(連結)",
  "pdfUrl": "https://www.release.tdnet.info/inbs/140120250919560459.pdf",
  "src": "TDnet",
  "hasXbrl": true,
  "genre": "kessan",
  "tags": [
   "決算短信"
  ],
  "isCorrection": false,
  "market": "グロース"
 },
 {
  "id": "tdnet-1196011",
  "date": "2025-10-14",
  "time": "16:00",
  "code": "1401",
  "name": "株式会社エムビーエス",
  "exch": "東",
  "title": "2026年５月期第１四半期決算短信〔日本基準〕(非連結)",
  "pdfUrl": "https://www.release.tdnet.info/inbs/140120251014572413.pdf",
  "src": "TDnet",
  "hasXbrl": true,
  "genre": "kessan",
  "tags": [
   "決算短信"
  ],
  "isCorrection": false,
  "market": "グロース"
 },
 {
  "id": "tdnet-1196009",
  "date": "2025-10-14",
  "time": "16:00",
  "code": "135A",
  "name": "株式会社ＶＲＡＩＮ　Ｓｏｌｕｔｉｏｎ",
  "exch": "東",
  "title": "2026年２月期 第２四半期（中間期）決算短信〔日本基準〕(非連結)",
  "pdfUrl": "https://www.release.tdnet.info/inbs/140120251008570370.pdf",
  "src": "TDnet",
  "hasXbrl": true,
  "genre": "kessan",
  "tags": [
   "決算短信"
  ],
  "isCorrection": false,
  "market": "グロース"
 },
 {
  "id": "tdnet-1196091",
  "date": "2025-10-14",
  "time": "15:55",
  "code": "6566",
  "name": "株式会社要興業",
  "exch": "東",
  "title": "株式の売出し、主要株主である筆頭株主及びその他の関係会社の異動、並びに 大栄環境株式会社との業務提携契約の締結に関するお知らせ",
  "pdfUrl": "https://www.release.tdnet.info/inbs/140120251014572402.pdf",
  "src": "TDnet",
  "hasXbrl": false,
  "genre": "release",
  "tags": [
   "業務提携"
  ],
  "isCorrection": false,
  "market": "スタンダード"
 },
 {
  "id": "tdnet-1195814",
  "date": "2025-10-14",
  "time": "15:40",
  "code": "9336",
  "name": "大栄環境株式会社",
  "exch": "東",
  "title": "第三者割当による自己株式処分（現物出資）及び株式会社要興業（証券コード：6566）の一部株式取得による持分法適用関連会社化に関するお知らせ",
  "pdfUrl": "https://www.release.tdnet.info/inbs/140120251014572575.pdf",
  "src": "TDnet",
  "hasXbrl": false,
  "genre": "ma",
  "tags": [
   "株式取得"
  ],
  "isCorrection": false,
  "market": "プライム"
 },
 {
  "id": "tdnet-1195813",
  "date": "2025-10-14",
  "time": "15:40",
  "code": "9336",
  "name": "大栄環境株式会社",
  "exch": "東",
  "title": "株式会社要興業（証券コード：6566）株式の買集め行為に該当する株式取得についてのお知らせ",
  "pdfUrl": "https://www.release.tdnet.info/inbs/140120251014572714.pdf",
  "src": "TDnet",
  "hasXbrl": false,
  "genre": "ma",
  "tags": [
   "株式取得"
  ],
  "isCorrection": false,
  "market": "プライム"
 },
 {
  "id": "tdnet-1196007",
  "date": "2025-10-14",
  "time": "15:30",
  "code": "9948",
  "name": "株式会社アークス",
  "exch": "東",
  "title": "自己株式取得に係る事項の決定に関するお知らせ （会社法第１６５条第２項の規定による定款の定めに基づく自己株式の取得）",
  "pdfUrl": "https://www.release.tdnet.info/inbs/140120251014572997.pdf",
  "src": "TDnet",
  "hasXbrl": false,
  "genre": "ma",
  "tags": [
   "株式取得"
  ],
  "isCorrection": false,
  "market": "プライム"
 },
 {
  "id": "tdnet-1196006",
  "date": "2025-10-14",
  "time": "15:30",
  "code": "9948",
  "name": "株式会社アークス",
  "exch": "東",
  "title": "2026年２月期 第２四半期（中間期）決算短信〔日本基準〕（連結）",
  "pdfUrl": "https://www.release.tdnet.info/inbs/140120251014572773.pdf",
  "src": "TDnet",
  "hasXbrl": true,
  "genre": "kessan",
  "tags": [
   "決算短信"
  ],
  "isCorrection": false,
  "market": "プライム"
 },
 {
  "id": "tdnet-1196004",
  "date": "2025-10-14",
  "time": "15:30",
  "code": "9278",
  "name": "ブックオフグループホールディングス株式会社",
  "exch": "東",
  "title": "2026年５月期  第１四半期決算短信〔日本基準〕（連結）",
  "pdfUrl": "https://www.release.tdnet.info/inbs/140120251014572891.pdf",
  "src": "TDnet",
  "hasXbrl": true,
  "genre": "kessan",
  "tags": [
   "決算短信"
  ],
  "isCorrection": false,
  "market": "プライム"
 },
 {
  "id": "tdnet-1196002",
  "date": "2025-10-14",
  "time": "15:30",
  "code": "9168",
  "name": "株式会社ライズ・コンサルティング・グループ",
  "exch": "東",
  "title": "2026年２月期　第２四半期(中間期)決算短信〔ＩＦＲＳ〕（連結）",
  "pdfUrl": "https://www.release.tdnet.info/inbs/140120251014572452.pdf",
  "src": "TDnet",
  "hasXbrl": true,
  "genre": "kessan",
  "tags": [
   "決算短信"
  ],
  "isCorrection": false,
  "market": "グロース"
 },
 {
  "id": "tdnet-1195994",
  "date": "2025-10-14",
  "time": "15:30",
  "code": "8904",
  "name": "株式会社ＡＶＡＮＴＩＡ",
  "exch": "東",
  "title": "中期経営計画2028（2026年8月期～2028年8月期）の策定に関するお知らせ",
  "pdfUrl": "https://www.release.tdnet.info/inbs/140120251009571101.pdf",
  "src": "TDnet",
  "hasXbrl": false,
  "genre": "chukei",
  "tags": [
   "中期経営計画"
  ],
  "isCorrection": false,
  "market": "スタンダード"
 },
 {
  "id": "tdnet-1195993",
  "date": "2025-10-14",
  "time": "15:30",
  "code": "8904",
  "name": "株式会社ＡＶＡＮＴＩＡ",
  "exch": "東",
  "title": "2025年8月期 決算短信〔日本基準〕（連結）",
  "pdfUrl": "https://www.release.tdnet.info/inbs/140120251009571056.pdf",
  "src": "TDnet",
  "hasXbrl": true,
  "genre": "kessan",
  "tags": [
   "決算短信"
  ],
  "isCorrection": false,
  "market": "スタンダード"
 },
 {
  "id": "tdnet-1195992",
  "date": "2025-10-14",
  "time": "15:30",
  "code": "8410",
  "name": "株式会社セブン銀行",
  "exch": "東",
  "title": "伊藤忠商事株式会社との資本業務提携に伴う第三者割当による自己株式処分の払込完了に関するお知らせ",
  "pdfUrl": "https://www.release.tdnet.info/inbs/140120251014572653.pdf",
  "src": "TDnet",
  "hasXbrl": false,
  "genre": "ma",
  "tags": [
   "資本業務提携"
  ],
  "isCorrection": false,
  "market": "プライム"
 },
 {
  "id": "tdnet-1195991",
  "date": "2025-10-14",
  "time": "15:30",
  "code": "8273",
  "name": "株式会社イズミ",
  "exch": "東",
  "title": "通期業績予想並びに第二次中期経営計画の数値目標修正に関するお知らせ",
  "pdfUrl": "https://www.release.tdnet.info/inbs/140120251010572181.pdf",
  "src": "TDnet",
  "hasXbrl": false,
  "genre": "chukei",
  "tags": [
   "中期経営計画"
  ],
  "isCorrection": false,
  "market": "プライム"
 },
 {
  "id": "tdnet-1195988",
  "date": "2025-10-14",
  "time": "15:30",
  "code": "8273",
  "name": "株式会社イズミ",
  "exch": "東",
  "title": "2026年２月期 第２四半期（中間期） 決算短信〔日本基準〕(連結)",
  "pdfUrl": "https://www.release.tdnet.info/inbs/140120251010572214.pdf",
  "src": "TDnet",
  "hasXbrl": true,
  "genre": "kessan",
  "tags": [
   "決算短信"
  ],
  "isCorrection": false,
  "market": "プライム"
 },
 {
  "id": "tdnet-1195981",
  "date": "2025-10-14",
  "time": "15:30",
  "code": "7928",
  "name": "旭化学工業株式会社",
  "exch": "東",
  "title": "2025年８月期 決算短信〔日本基準〕（連結）",
  "pdfUrl": "https://www.release.tdnet.info/inbs/140120250926563011.pdf",
  "src": "TDnet",
  "hasXbrl": true,
  "genre": "kessan",
  "tags": [
   "決算短信"
  ],
  "isCorrection": false,
  "market": "スタンダード"
 },
 {
  "id": "tdnet-1195977",
  "date": "2025-10-14",
  "time": "15:30",
  "code": "7599",
  "name": "株式会社ＩＤＯＭ",
  "exch": "東",
  "title": "2026年２月期  第２四半期（中間期）決算短信〔日本基準〕（連結）",
  "pdfUrl": "https://www.release.tdnet.info/inbs/140120251007569622.pdf",
  "src": "TDnet",
  "hasXbrl": true,
  "genre": "kessan",
  "tags": [
   "決算短信"
  ],
  "isCorrection": false,
  "market": "プライム"
 },
 {
  "id": "tdnet-1195974",
  "date": "2025-10-14",
  "time": "15:30",
  "code": "7512",
  "name": "イオン北海道株式会社",
  "exch": "東",
  "title": "2026年2月期 第2四半期（中間期）決算短信〔日本基準〕（非連結）",
  "pdfUrl": "https://www.release.tdnet.info/inbs/140120251009571162.pdf",
  "src": "TDnet",
  "hasXbrl": true,
  "genre": "kessan",
  "tags": [
   "決算短信"
  ],
  "isCorrection": false,
  "market": "スタンダード"
 },
 {
  "id": "tdnet-1195971",
  "date": "2025-10-14",
  "time": "15:30",
  "code": "7467",
  "name": "萩原電気ホールディングス株式会社",
  "exch": "東",
  "title": "共同持株会社設立（株式移転）による経営統合に関する経営統合契約書の締結及び株式移転計画の作成に関するお知らせ",
  "pdfUrl": "https://www.release.tdnet.info/inbs/140120251014572364.pdf",
  "src": "TDnet",
  "hasXbrl": false,
  "genre": "ma",
  "tags": [
   "経営統合",
   "株式移転"
  ],
  "isCorrection": false,
  "market": "不明"
 },
 {
  "id": "tdnet-1195970",
  "date": "2025-10-14",
  "time": "15:30",
  "code": "7420",
  "name": "佐鳥電機株式会社",
  "exch": "東",
  "title": "2026年５月期第１四半期決算短信〔日本基準〕(連結)",
  "pdfUrl": "https://www.release.tdnet.info/inbs/140120251014573161.pdf",
  "src": "TDnet",
  "hasXbrl": true,
  "genre": "kessan",
  "tags": [
   "決算短信"
  ],
  "isCorrection": false,
  "market": "不明"
 },
 {
  "id": "tdnet-1195968",
  "date": "2025-10-14",
  "time": "15:30",
  "code": "7420",
  "name": "佐鳥電機株式会社",
  "exch": "東",
  "title": "共同持株会社設立（株式移転）による経営統合に関する経営統合契約書の締結及び株式移転計画の作成に関するお知らせ",
  "pdfUrl": "https://www.release.tdnet.info/inbs/140120251014573087.pdf",
  "src": "TDnet",
  "hasXbrl": false,
  "genre": "ma",
  "tags": [
   "経営統合",
   "株式移転"
  ],
  "isCorrection": false,
  "market": "不明"
 },
 {
  "id": "tdnet-1195965",
  "date": "2025-10-14",
  "time": "15:30",
  "code": "7370",
  "name": "株式会社Ｅｎｊｉｎ",
  "exch": "東",
  "title": "2026年５月期第１四半期決算短信〔日本基準〕(連結)",
  "pdfUrl": "https://www.release.tdnet.info/inbs/140120251010571924.pdf",
  "src": "TDnet",
  "hasXbrl": true,
  "genre": "kessan",
  "tags": [
   "決算短信"
  ],
  "isCorrection": false,
  "market": "グロース"
 },
 {
  "id": "tdnet-1195962",
  "date": "2025-10-14",
  "time": "15:30",
  "code": "7077",
  "name": "株式会社ＡＬｉＮＫインターネット",
  "exch": "東",
  "title": "2026年２月期 第２四半期（中間期）決算短信〔日本基準〕(連結)",
  "pdfUrl": "https://www.release.tdnet.info/inbs/140120251014572495.pdf",
  "src": "TDnet",
  "hasXbrl": true,
  "genre": "kessan",
  "tags": [
   "決算短信"
  ],
  "isCorrection": false,
  "market": "グロース"
 },
 {
  "id": "tdnet-1195960",
  "date": "2025-10-14",
  "time": "15:30",
  "code": "7077",
  "name": "株式会社ＡＬｉＮＫインターネット",
  "exch": "東",
  "title": "(訂正・数値データ訂正)「2026年２月期 第１四半期決算短信〔日本基準〕(連結)」の一部訂正について",
  "pdfUrl": "https://www.release.tdnet.info/inbs/140120251010571434.pdf",
  "src": "TDnet",
  "hasXbrl": true,
  "genre": "kessan",
  "tags": [
   "決算短信"
  ],
  "isCorrection": true,
  "market": "グロース"
 },
 {
  "id": "tdnet-1195957",
  "date": "2025-10-14",
  "time": "15:30",
  "code": "6634",
  "name": "株式会社ネクスグループ",
  "exch": "東",
  "title": "2025年11月期第３四半期決算短信〔日本基準〕(連結)",
  "pdfUrl": "https://www.release.tdnet.info/inbs/140120251010572082.pdf",
  "src": "TDnet",
  "hasXbrl": true,
  "genre": "kessan",
  "tags": [
   "決算短信"
  ],
  "isCorrection": false,
  "market": "スタンダード"
 },
 {
  "id": "tdnet-1195949",
  "date": "2025-10-14",
  "time": "15:30",
  "code": "5885",
  "name": "株式会社ジーデップ・アドバンス",
  "exch": "東",
  "title": "2026年5月期第1四半期決算短信〔日本基準〕（非連結）",
  "pdfUrl": "https://www.release.tdnet.info/inbs/140120251010571719.pdf",
  "src": "TDnet",
  "hasXbrl": true,
  "genre": "kessan",
  "tags": [
   "決算短信"
  ],
  "isCorrection": false,
  "market": "スタンダード"
 },
 {
  "id": "tdnet-1195948",
  "date": "2025-10-14",
  "time": "15:30",
  "code": "5851",
  "name": "リョービ株式会社",
  "exch": "東",
  "title": "自己株式取得に係る事項の決定に関するお知らせ",
  "pdfUrl": "https://www.release.tdnet.info/inbs/140120251014572576.pdf",
  "src": "TDnet",
  "hasXbrl": false,
  "genre": "ma",
  "tags": [
   "株式取得"
  ],
  "isCorrection": false,
  "market": "プライム"
 },
 {
  "id": "tdnet-1195945",
  "date": "2025-10-14",
  "time": "15:30",
  "code": "5581",
  "name": "株式会社カイテクノロジー",
  "exch": "東",
  "title": "2025年８月期決算短信〔日本基準〕(連結)",
  "pdfUrl": "https://www.release.tdnet.info/inbs/140120251014572425.pdf",
  "src": "TDnet",
  "hasXbrl": false,
  "genre": "kessan",
  "tags": [
   "決算短信"
  ],
  "isCorrection": false,
  "market": "不明"
 },
 {
  "id": "tdnet-1195940",
  "date": "2025-10-14",
  "time": "15:30",
  "code": "5577",
  "name": "株式会社アイデミー",
  "exch": "東",
  "title": "2026年５月期 第１四半期決算短信〔日本基準〕（連結）",
  "pdfUrl": "https://www.release.tdnet.info/inbs/140120251014573007.pdf",
  "src": "TDnet",
  "hasXbrl": true,
  "genre": "kessan",
  "tags": [
   "決算短信"
  ],
  "isCorrection": false,
  "market": "不明"
 },
 {
  "id": "tdnet-1195937",
  "date": "2025-10-14",
  "time": "15:30",
  "code": "5250",
  "name": "プライム・ストラテジー株式会社",
  "exch": "東",
  "title": "2025年11月期　第３四半期決算短信〔日本基準〕（連結）",
  "pdfUrl": "https://www.release.tdnet.info/inbs/140120251014572375.pdf",
  "src": "TDnet",
  "hasXbrl": true,
  "genre": "kessan",
  "tags": [
   "決算短信"
  ],
  "isCorrection": false,
  "market": "スタンダード"
 },
 {
  "id": "tdnet-1195935",
  "date": "2025-10-14",
  "time": "15:30",
  "code": "4593",
  "name": "株式会社ヘリオス",
  "exch": "東",
  "title": "株式会社ニコンとの業務・資本提携契約解除に関するお知らせ",
  "pdfUrl": "https://www.release.tdnet.info/inbs/140120251014572666.pdf",
  "src": "TDnet",
  "hasXbrl": false,
  "genre": "ma",
  "tags": [
   "資本提携"
  ],
  "isCorrection": false,
  "market": "グロース"
 },
 {
  "id": "tdnet-1195933",
  "date": "2025-10-14",
  "time": "15:30",
  "code": "4433",
  "name": "株式会社ヒト・コミュニケーションズ・ホールディングス",
  "exch": "東",
  "title": "2025年8月期 決算短信〔日本基準〕(連結)",
  "pdfUrl": "https://www.release.tdnet.info/inbs/140120251013572294.pdf",
  "src": "TDnet",
  "hasXbrl": true,
  "genre": "kessan",
  "tags": [
   "決算短信"
  ],
  "isCorrection": false,
  "market": "プライム"
 },
 {
  "id": "tdnet-1195929",
  "date": "2025-10-14",
  "time": "15:30",
  "code": "4343",
  "name": "株式会社イオンファンタジー",
  "exch": "東",
  "title": "2026年２月期第２四半期（中間期）決算短信〔日本基準〕(連結)",
  "pdfUrl": "https://www.release.tdnet.info/inbs/140120251014572946.pdf",
  "src": "TDnet",
  "hasXbrl": true,
  "genre": "kessan",
  "tags": [
   "決算短信"
  ],
  "isCorrection": false,
  "market": "プライム"
 },
 {
  "id": "tdnet-1195928",
  "date": "2025-10-14",
  "time": "15:30",
  "code": "4317",
  "name": "株式会社レイ",
  "exch": "東",
  "title": "令和８年２月期第２四半期（中間期）決算短信〔日本基準〕(連結)",
  "pdfUrl": "https://www.release.tdnet.info/inbs/140120251014572487.pdf",
  "src": "TDnet",
  "hasXbrl": true,
  "genre": "kessan",
  "tags": [
   "決算短信"
  ],
  "isCorrection": false,
  "market": "スタンダード"
 },
 {
  "id": "tdnet-1195927",
  "date": "2025-10-14",
  "time": "15:30",
  "code": "4199",
  "name": "ワンダープラネット株式会社",
  "exch": "東",
  "title": "2025年8月期 通期決算説明資料（事業計画および成長可能性に関する事項）",
  "pdfUrl": "https://www.release.tdnet.info/inbs/140120251014572805.pdf",
  "src": "TDnet",
  "hasXbrl": false,
  "genre": "chukei",
  "tags": [
   "成長可能性に関する事項"
  ],
  "isCorrection": false,
  "market": "グロース"
 },
 {
  "id": "tdnet-1195926",
  "date": "2025-10-14",
  "time": "15:30",
  "code": "4199",
  "name": "ワンダープラネット株式会社",
  "exch": "東",
  "title": "2025年8月期 決算短信〔日本基準〕(非連結)",
  "pdfUrl": "https://www.release.tdnet.info/inbs/140120251010571487.pdf",
  "src": "TDnet",
  "hasXbrl": true,
  "genre": "kessan",
  "tags": [
   "決算短信"
  ],
  "isCorrection": false,
  "market": "グロース"
 },
 {
  "id": "tdnet-1195925",
  "date": "2025-10-14",
  "time": "15:30",
  "code": "4198",
  "name": "株式会社テンダ",
  "exch": "東",
  "title": "2026年５月期第１四半期決算短信〔日本基準〕(連結)",
  "pdfUrl": "https://www.release.tdnet.info/inbs/140120251014572389.pdf",
  "src": "TDnet",
  "hasXbrl": true,
  "genre": "kessan",
  "tags": [
   "決算短信"
  ],
  "isCorrection": false,
  "market": "スタンダード"
 },
 {
  "id": "tdnet-1195924",
  "date": "2025-10-14",
  "time": "15:30",
  "code": "3996",
  "name": "サインポスト株式会社",
  "exch": "東",
  "title": "2026年2月期 第2四半期 (中間期) 決算短信〔日本基準〕(非連結)",
  "pdfUrl": "https://www.release.tdnet.info/inbs/140120251010571595.pdf",
  "src": "TDnet",
  "hasXbrl": true,
  "genre": "kessan",
  "tags": [
   "決算短信"
  ],
  "isCorrection": false,
  "market": "スタンダード"
 },
 {
  "id": "tdnet-1195919",
  "date": "2025-10-14",
  "time": "15:30",
  "code": "3987",
  "name": "エコモット株式会社",
  "exch": "東",
  "title": "2025年8月期決算短信〔日本基準〕（連結）",
  "pdfUrl": "https://www.release.tdnet.info/inbs/140120251014572564.pdf",
  "src": "TDnet",
  "hasXbrl": true,
  "genre": "kessan",
  "tags": [
   "決算短信"
  ],
  "isCorrection": false,
  "market": "グロース"
 },
 {
  "id": "tdnet-1195915",
  "date": "2025-10-14",
  "time": "15:30",
  "code": "3977",
  "name": "フュージョン株式会社",
  "exch": "札",
  "title": "2026年２月期 第２四半期（中間期）決算短信［日本基準］（非連結）",
  "pdfUrl": "https://www.release.tdnet.info/inbs/140120251010571899.pdf",
  "src": "TDnet",
  "hasXbrl": true,
  "genre": "kessan",
  "tags": [
   "決算短信"
  ],
  "isCorrection": false,
  "market": "地方"
 },
 {
  "id": "tdnet-1195913",
  "date": "2025-10-14",
  "time": "15:30",
  "code": "3922",
  "name": "株式会社ＰＲ　ＴＩＭＥＳ",
  "exch": "東",
  "title": "2026年２月期 第２四半期（中間期）決算短信〔日本基準〕（連結）",
  "pdfUrl": "https://www.release.tdnet.info/inbs/140120251014572494.pdf",
  "src": "TDnet",
  "hasXbrl": true,
  "genre": "kessan",
  "tags": [
   "決算短信"
  ],
  "isCorrection": false,
  "market": "プライム"
 },
 {
  "id": "tdnet-1195908",
  "date": "2025-10-14",
  "time": "15:30",
  "code": "3697",
  "name": "株式会社ＳＨＩＦＴ",
  "exch": "東",
  "title": "株式会社SHIFTグロース・キャピタルとの会社分割（簡易吸収分割）及び株式会社KINSHAの吸収合併（簡易吸収合併）に関するお知らせ",
  "pdfUrl": "https://www.release.tdnet.info/inbs/140120251014572866.pdf",
  "src": "TDnet",
  "hasXbrl": false,
  "genre": "ma",
  "tags": [
   "吸収合併",
   "会社分割"
  ],
  "isCorrection": false,
  "market": "プライム"
 },
 {
  "id": "tdnet-1195905",
  "date": "2025-10-14",
  "time": "15:30",
  "code": "3697",
  "name": "株式会社ＳＨＩＦＴ",
  "exch": "東",
  "title": "2025年８月期　決算短信〔日本基準〕(連結)",
  "pdfUrl": "https://www.release.tdnet.info/inbs/140120251014572712.pdf",
  "src": "TDnet",
  "hasXbrl": true,
  "genre": "kessan",
  "tags": [
   "決算短信"
  ],
  "isCorrection": false,
  "market": "プライム"
 },
 {
  "id": "tdnet-1195903",
  "date": "2025-10-14",
  "time": "15:30",
  "code": "3608",
  "name": "株式会社ＴＳＩホールディングス",
  "exch": "東",
  "title": "2026年２月期 第２四半期（中間期）決算短信〔日本基準〕(連結)",
  "pdfUrl": "https://www.release.tdnet.info/inbs/140120251007569521.pdf",
  "src": "TDnet",
  "hasXbrl": true,
  "genre": "kessan",
  "tags": [
   "決算短信"
  ],
  "isCorrection": false,
  "market": "プライム"
 },
 {
  "id": "tdnet-1195899",
  "date": "2025-10-14",
  "time": "15:30",
  "code": "3562",
  "name": "株式会社Ｎｏ．１",
  "exch": "東",
  "title": "2026年２月期　第２四半期（中間期）決算短信〔日本基準〕（連結）",
  "pdfUrl": "https://www.release.tdnet.info/inbs/140120251010572017.pdf",
  "src": "TDnet",
  "hasXbrl": true,
  "genre": "kessan",
  "tags": [
   "決算短信"
  ],
  "isCorrection": false,
  "market": "スタンダード"
 },
 {
  "id": "tdnet-1195898",
  "date": "2025-10-14",
  "time": "15:30",
  "code": "3541",
  "name": "株式会社農業総合研究所",
  "exch": "東",
  "title": "2025年８月期　決算説明資料（事業計画及び成長可能性に関する事項）",
  "pdfUrl": "https://www.release.tdnet.info/inbs/140120251010572215.pdf",
  "src": "TDnet",
  "hasXbrl": false,
  "genre": "chukei",
  "tags": [
   "成長可能性に関する事項"
  ],
  "isCorrection": false,
  "market": "不明"
 },
 {
  "id": "tdnet-1195896",
  "date": "2025-10-14",
  "time": "15:30",
  "code": "3541",
  "name": "株式会社農業総合研究所",
  "exch": "東",
  "title": "2025年８月期　決算短信［日本基準］（非連結）",
  "pdfUrl": "https://www.release.tdnet.info/inbs/140120251010572212.pdf",
  "src": "TDnet",
  "hasXbrl": true,
  "genre": "kessan",
  "tags": [
   "決算短信"
  ],
  "isCorrection": false,
  "market": "不明"
 },
 {
  "id": "tdnet-1195894",
  "date": "2025-10-14",
  "time": "15:30",
  "code": "353A",
  "name": "エレベーターコミュニケーションズ株式会社",
  "exch": "札",
  "title": "2026年５月期 第１四半期 決算短信〔日本基準〕（非連結）",
  "pdfUrl": "https://www.release.tdnet.info/inbs/140120251014572388.pdf",
  "src": "TDnet",
  "hasXbrl": true,
  "genre": "kessan",
  "tags": [
   "決算短信"
  ],
  "isCorrection": false,
  "market": "地方"
 },
 {
  "id": "tdnet-1195891",
  "date": "2025-10-14",
  "time": "15:30",
  "code": "340A",
  "name": "株式会社ジグザグ",
  "exch": "東",
  "title": "2026年５月期第１四半期決算短信〔日本基準〕（非連結）",
  "pdfUrl": "https://www.release.tdnet.info/inbs/140120251014572438.pdf",
  "src": "TDnet",
  "hasXbrl": true,
  "genre": "kessan",
  "tags": [
   "決算短信"
  ],
  "isCorrection": false,
  "market": "グロース"
 },
 {
  "id": "tdnet-1195889",
  "date": "2025-10-14",
  "time": "15:30",
  "code": "339A",
  "name": "プログレス・テクノロジーズ　グループ株式会社",
  "exch": "東",
  "title": "2026年２月期 第２四半期（中間期）決算短信〔ＩＦＲＳ〕（連結）",
  "pdfUrl": "https://www.release.tdnet.info/inbs/140120251014572738.pdf",
  "src": "TDnet",
  "hasXbrl": true,
  "genre": "kessan",
  "tags": [
   "決算短信"
  ],
  "isCorrection": false,
  "market": "グロース"
 },
 {
  "id": "tdnet-1195887",
  "date": "2025-10-14",
  "time": "15:30",
  "code": "3349",
  "name": "株式会社コスモス薬品",
  "exch": "東",
  "title": "2026年５月期　第１四半期決算短信〔日本基準〕（連結）",
  "pdfUrl": "https://www.release.tdnet.info/inbs/140120251009570542.pdf",
  "src": "TDnet",
  "hasXbrl": true,
  "genre": "kessan",
  "tags": [
   "決算短信"
  ],
  "isCorrection": false,
  "market": "プライム"
 },
 {
  "id": "tdnet-1195885",
  "date": "2025-10-14",
  "time": "15:30",
  "code": "3346",
  "name": "ヒロタグループホールディングス株式会社",
  "exch": "名",
  "title": "連結子会社の異動（株式譲渡）に関するお知らせ",
  "pdfUrl": "https://www.release.tdnet.info/inbs/140120251014573090.pdf",
  "src": "TDnet",
  "hasXbrl": false,
  "genre": "ma",
  "tags": [
   "株式譲渡",
   "子会社の異動"
  ],
  "isCorrection": false,
  "market": "地方"
 },
 {
  "id": "tdnet-1195884",
  "date": "2025-10-14",
  "time": "15:30",
  "code": "3297",
  "name": "株式会社東武住販",
  "exch": "東",
  "title": "2026年５月期第１四半期決算短信〔日本基準〕(非連結)",
  "pdfUrl": "https://www.release.tdnet.info/inbs/140120251014572781.pdf",
  "src": "TDnet",
  "hasXbrl": true,
  "genre": "kessan",
  "tags": [
   "決算短信"
  ],
  "isCorrection": false,
  "market": "スタンダード"
 },
 {
  "id": "tdnet-1195880",
  "date": "2025-10-14",
  "time": "15:30",
  "code": "3281",
  "name": "Ｒ－ＧＬＰ",
  "exch": "東",
  "title": "2025年8月期 決算短信(REIT)",
  "pdfUrl": "https://www.release.tdnet.info/inbs/140120251014572968.pdf",
  "src": "TDnet",
  "hasXbrl": true,
  "genre": "kessan",
  "tags": [
   "決算短信"
  ],
  "isCorrection": false,
  "market": "不明"
 },
 {
  "id": "tdnet-1195878",
  "date": "2025-10-14",
  "time": "15:30",
  "code": "3236",
  "name": "株式会社プロパスト",
  "exch": "東",
  "title": "2026年5月期 第1四半期決算短信〔日本基準〕（非連結）",
  "pdfUrl": "https://www.release.tdnet.info/inbs/140120251014572975.pdf",
  "src": "TDnet",
  "hasXbrl": true,
  "genre": "kessan",
  "tags": [
   "決算短信"
  ],
  "isCorrection": false,
  "market": "スタンダード"
 },
 {
  "id": "tdnet-1195877",
  "date": "2025-10-14",
  "time": "15:30",
  "code": "3198",
  "name": "ＳＦＰホールディングス株式会社",
  "exch": "東",
  "title": "２０２６年２月期　第２四半期（中間期）決算短信〔日本基準〕(連結)",
  "pdfUrl": "https://www.release.tdnet.info/inbs/140120251007569694.pdf",
  "src": "TDnet",
  "hasXbrl": true,
  "genre": "kessan",
  "tags": [
   "決算短信"
  ],
  "isCorrection": false,
  "market": "不明"
 },
 {
  "id": "tdnet-1195872",
  "date": "2025-10-14",
  "time": "15:30",
  "code": "3139",
  "name": "株式会社ラクト・ジャパン",
  "exch": "東",
  "title": "2025年11月期第３四半期決算短信〔日本基準〕(連結)",
  "pdfUrl": "https://www.release.tdnet.info/inbs/140120251007569316.pdf",
  "src": "TDnet",
  "hasXbrl": true,
  "genre": "kessan",
  "tags": [
   "決算短信"
  ],
  "isCorrection": false,
  "market": "プライム"
 },
 {
  "id": "tdnet-1195870",
  "date": "2025-10-14",
  "time": "15:30",
  "code": "3087",
  "name": "株式会社ドトール・日レスホールディングス",
  "exch": "東",
  "title": "2026年２月期 第２四半期（中間期）決算短信〔日本基準〕（連結）",
  "pdfUrl": "https://www.release.tdnet.info/inbs/140120251014572895.pdf",
  "src": "TDnet",
  "hasXbrl": true,
  "genre": "kessan",
  "tags": [
   "決算短信"
  ],
  "isCorrection": false,
  "market": "プライム"
 },
 {
  "id": "tdnet-1195867",
  "date": "2025-10-14",
  "time": "15:30",
  "code": "3086",
  "name": "Ｊ．フロント　リテイリング株式会社",
  "exch": "東",
  "title": "2026年２月期　第２四半期（中間期）決算短信〔ＩＦＲＳ〕（連結）",
  "pdfUrl": "https://www.release.tdnet.info/inbs/140120251010571771.pdf",
  "src": "TDnet",
  "hasXbrl": true,
  "genre": "kessan",
  "tags": [
   "決算短信"
  ],
  "isCorrection": false,
  "market": "プライム"
 },
 {
  "id": "tdnet-1195866",
  "date": "2025-10-14",
  "time": "15:30",
  "code": "3045",
  "name": "株式会社カワサキ",
  "exch": "東",
  "title": "2025年８月期 決算短信〔日本基準〕(非連結)",
  "pdfUrl": "https://www.release.tdnet.info/inbs/140120251009571017.pdf",
  "src": "TDnet",
  "hasXbrl": true,
  "genre": "kessan",
  "tags": [
   "決算短信"
  ],
  "isCorrection": false,
  "market": "スタンダード"
 },
 {
  "id": "tdnet-1195864",
  "date": "2025-10-14",
  "time": "15:30",
  "code": "2936",
  "name": "ベースフード株式会社",
  "exch": "東",
  "title": "2026年２月期 第２四半期決算短信〔日本基準〕 （非連結）",
  "pdfUrl": "https://www.release.tdnet.info/inbs/140120251014572599.pdf",
  "src": "TDnet",
  "hasXbrl": true,
  "genre": "kessan",
  "tags": [
   "決算短信"
  ],
  "isCorrection": false,
  "market": "グロース"
 },
 {
  "id": "tdnet-1195862",
  "date": "2025-10-14",
  "time": "15:30",
  "code": "2791",
  "name": "大黒天物産株式会社",
  "exch": "東",
  "title": "2026年5月期第1四半期決算短信〔日本基準〕（連結）",
  "pdfUrl": "https://www.release.tdnet.info/inbs/140120251014572752.pdf",
  "src": "TDnet",
  "hasXbrl": true,
  "genre": "kessan",
  "tags": [
   "決算短信"
  ],
  "isCorrection": false,
  "market": "プライム"
 },
 {
  "id": "tdnet-1195859",
  "date": "2025-10-14",
  "time": "15:30",
  "code": "276A",
  "name": "ククレブ・アドバイザーズ株式会社",
  "exch": "東",
  "title": "ファイブ・アンド・ミライアソシエイツ株式会社との業務提携に関するお知らせ",
  "pdfUrl": "https://www.release.tdnet.info/inbs/140120251010572047.pdf",
  "src": "TDnet",
  "hasXbrl": false,
  "genre": "release",
  "tags": [
   "業務提携"
  ],
  "isCorrection": false,
  "market": "グロース"
 },
 {
  "id": "tdnet-1195858",
  "date": "2025-10-14",
  "time": "15:30",
  "code": "276A",
  "name": "ククレブ・アドバイザーズ株式会社",
  "exch": "東",
  "title": "中期経営計画の策定に関するお知らせ",
  "pdfUrl": "https://www.release.tdnet.info/inbs/140120251010571705.pdf",
  "src": "TDnet",
  "hasXbrl": false,
  "genre": "chukei",
  "tags": [
   "中期経営計画"
  ],
  "isCorrection": false,
  "market": "グロース"
 },
 {
  "id": "tdnet-1195856",
  "date": "2025-10-14",
  "time": "15:30",
  "code": "276A",
  "name": "ククレブ・アドバイザーズ株式会社",
  "exch": "東",
  "title": "2025年８月期決算短信〔日本基準〕(連結)",
  "pdfUrl": "https://www.release.tdnet.info/inbs/140120251010572124.pdf",
  "src": "TDnet",
  "hasXbrl": true,
  "genre": "kessan",
  "tags": [
   "決算短信"
  ],
  "isCorrection": false,
  "market": "グロース"
 },
 {
  "id": "tdnet-1195854",
  "date": "2025-10-14",
  "time": "15:30",
  "code": "2686",
  "name": "株式会社ジーフット",
  "exch": "東",
  "title": "2026年２月期 第２四半期（中間期）決算短信〔日本基準〕（連結）",
  "pdfUrl": "https://www.release.tdnet.info/inbs/140120251014572791.pdf",
  "src": "TDnet",
  "hasXbrl": true,
  "genre": "kessan",
  "tags": [
   "決算短信"
  ],
  "isCorrection": false,
  "market": "不明"
 },
 {
  "id": "tdnet-1195852",
  "date": "2025-10-14",
  "time": "15:30",
  "code": "2683",
  "name": "株式会社魚喜",
  "exch": "東",
  "title": "2026年2月期　第2四半期（中間期）決算短信〔日本基準〕（連結）",
  "pdfUrl": "https://www.release.tdnet.info/inbs/140120250930565485.pdf",
  "src": "TDnet",
  "hasXbrl": true,
  "genre": "kessan",
  "tags": [
   "決算短信"
  ],
  "isCorrection": false,
  "market": "スタンダード"
 },
 {
  "id": "tdnet-1195849",
  "date": "2025-10-14",
  "time": "15:30",
  "code": "2653",
  "name": "イオン九州株式会社",
  "exch": "東",
  "title": "2026年２月期 第２四半期（中間期）決算短信〔日本基準〕（連結）",
  "pdfUrl": "https://www.release.tdnet.info/inbs/140120251013572266.pdf",
  "src": "TDnet",
  "hasXbrl": true,
  "genre": "kessan",
  "tags": [
   "決算短信"
  ],
  "isCorrection": false,
  "market": "スタンダード"
 },
 {
  "id": "tdnet-1195846",
  "date": "2025-10-14",
  "time": "15:30",
  "code": "2471",
  "name": "株式会社エスプール",
  "exch": "東",
  "title": "2025年11月期　第３四半期決算短信〔IFRS〕（連結）",
  "pdfUrl": "https://www.release.tdnet.info/inbs/140120251010572137.pdf",
  "src": "TDnet",
  "hasXbrl": true,
  "genre": "kessan",
  "tags": [
   "決算短信"
  ],
  "isCorrection": false,
  "market": "プライム"
 },
 {
  "id": "tdnet-1195845",
  "date": "2025-10-14",
  "time": "15:30",
  "code": "2462",
  "name": "ライク株式会社",
  "exch": "東",
  "title": "2026年５月期 第１四半期決算短信〔日本基準〕（連結）",
  "pdfUrl": "https://www.release.tdnet.info/inbs/140120251010572223.pdf",
  "src": "TDnet",
  "hasXbrl": true,
  "genre": "kessan",
  "tags": [
   "決算短信"
  ],
  "isCorrection": false,
  "market": "プライム"
 },
 {
  "id": "tdnet-1195843",
  "date": "2025-10-14",
  "time": "15:30",
  "code": "2379",
  "name": "ディップ株式会社",
  "exch": "東",
  "title": "2026年２月期第２四半期（中間期）決算短信〔日本基準〕（連結）",
  "pdfUrl": "https://www.release.tdnet.info/inbs/140120251008570070.pdf",
  "src": "TDnet",
  "hasXbrl": true,
  "genre": "kessan",
  "tags": [
   "決算短信"
  ],
  "isCorrection": false,
  "market": "プライム"
 },
 {
  "id": "tdnet-1195840",
  "date": "2025-10-14",
  "time": "15:30",
  "code": "2337",
  "name": "いちご株式会社",
  "exch": "東",
  "title": "2026年2月期 第2四半期（中間期）決算短信〔日本基準〕（連結）",
  "pdfUrl": "https://www.release.tdnet.info/inbs/140120251010571988.pdf",
  "src": "TDnet",
  "hasXbrl": true,
  "genre": "kessan",
  "tags": [
   "決算短信"
  ],
  "isCorrection": false,
  "market": "プライム"
 },
 {
  "id": "tdnet-1195837",
  "date": "2025-10-14",
  "time": "15:30",
  "code": "2305",
  "name": "株式会社スタジオアリス",
  "exch": "東",
  "title": "2026年2月期 第2四半期（中間期）決算短信〔日本基準〕（連結）",
  "pdfUrl": "https://www.release.tdnet.info/inbs/140120250929563870.pdf",
  "src": "TDnet",
  "hasXbrl": true,
  "genre": "kessan",
  "tags": [
   "決算短信"
  ],
  "isCorrection": false,
  "market": "スタンダード"
 },
 {
  "id": "tdnet-1195836",
  "date": "2025-10-14",
  "time": "15:30",
  "code": "2292",
  "name": "エスフーズ株式会社",
  "exch": "東",
  "title": "2026年２月期第２四半期（中間期）決算短信〔日本基準〕(連結)",
  "pdfUrl": "https://www.release.tdnet.info/inbs/140120251014572595.pdf",
  "src": "TDnet",
  "hasXbrl": true,
  "genre": "kessan",
  "tags": [
   "決算短信"
  ],
  "isCorrection": false,
  "market": "プライム"
 },
 {
  "id": "tdnet-1195834",
  "date": "2025-10-14",
  "time": "15:30",
  "code": "2207",
  "name": "株式会社ｍｅｉｔｏ",
  "exch": "東",
  "title": "2026年３月期 第１四半期決算短信〔日本基準〕（連結）（公認会計士等による期中レビューの完了）",
  "pdfUrl": "https://www.release.tdnet.info/inbs/140120251008569977.pdf",
  "src": "TDnet",
  "hasXbrl": true,
  "genre": "kessan",
  "tags": [
   "決算短信"
  ],
  "isCorrection": false,
  "market": "プライム"
 },
 {
  "id": "tdnet-1195833",
  "date": "2025-10-14",
  "time": "15:30",
  "code": "2207",
  "name": "株式会社ｍｅｉｔｏ",
  "exch": "東",
  "title": "配当予想および中期経営計画の配当金に関する経営指標（KPI）の修正に関するお知らせ",
  "pdfUrl": "https://www.release.tdnet.info/inbs/140120251009571055.pdf",
  "src": "TDnet",
  "hasXbrl": false,
  "genre": "chukei",
  "tags": [
   "中期経営計画"
  ],
  "isCorrection": false,
  "market": "プライム"
 },
 {
  "id": "tdnet-1195832",
  "date": "2025-10-14",
  "time": "15:30",
  "code": "2207",
  "name": "株式会社ｍｅｉｔｏ",
  "exch": "東",
  "title": "自己株式取得に係る事項の決定及び自己株式の消却に関するお知らせ",
  "pdfUrl": "https://www.release.tdnet.info/inbs/140120251009571053.pdf",
  "src": "TDnet",
  "hasXbrl": false,
  "genre": "ma",
  "tags": [
   "株式取得"
  ],
  "isCorrection": false,
  "market": "プライム"
 },
 {
  "id": "tdnet-1195831",
  "date": "2025-10-14",
  "time": "15:30",
  "code": "2207",
  "name": "株式会社ｍｅｉｔｏ",
  "exch": "東",
  "title": "中期経営計画の修正に関するお知らせ",
  "pdfUrl": "https://www.release.tdnet.info/inbs/140120251009571050.pdf",
  "src": "TDnet",
  "hasXbrl": false,
  "genre": "chukei",
  "tags": [
   "中期経営計画"
  ],
  "isCorrection": false,
  "market": "プライム"
 },
 {
  "id": "tdnet-1195829",
  "date": "2025-10-14",
  "time": "15:30",
  "code": "2186",
  "name": "ソーバル株式会社",
  "exch": "東",
  "title": "2026年２月期第２四半期（中間期）決算短信〔日本基準〕(連結)",
  "pdfUrl": "https://www.release.tdnet.info/inbs/140120251014572397.pdf",
  "src": "TDnet",
  "hasXbrl": true,
  "genre": "kessan",
  "tags": [
   "決算短信"
  ],
  "isCorrection": false,
  "market": "スタンダード"
 },
 {
  "id": "tdnet-1195825",
  "date": "2025-10-14",
  "time": "15:30",
  "code": "156A",
  "name": "マテリアルグループ株式会社",
  "exch": "東",
  "title": "中期経営計画（事業計画及び成長可能性に関する資料）",
  "pdfUrl": "https://www.release.tdnet.info/inbs/140120251014573138.pdf",
  "src": "TDnet",
  "hasXbrl": false,
  "genre": "chukei",
  "tags": [
   "中期経営計画"
  ],
  "isCorrection": false,
  "market": "グロース"
 },
 {
  "id": "tdnet-1195822",
  "date": "2025-10-14",
  "time": "15:30",
  "code": "156A",
  "name": "マテリアルグループ株式会社",
  "exch": "東",
  "title": "2025年8月期決算短信〔日本基準〕（連結）",
  "pdfUrl": "https://www.release.tdnet.info/inbs/140120251014573098.pdf",
  "src": "TDnet",
  "hasXbrl": true,
  "genre": "kessan",
  "tags": [
   "決算短信"
  ],
  "isCorrection": false,
  "market": "グロース"
 },
 {
  "id": "tdnet-1195820",
  "date": "2025-10-14",
  "time": "15:30",
  "code": "1419",
  "name": "タマホーム株式会社",
  "exch": "東",
  "title": "2026年５月期第１四半期 決算短信補足資料",
  "pdfUrl": "https://www.release.tdnet.info/inbs/140120251014572458.pdf",
  "src": "TDnet",
  "hasXbrl": false,
  "genre": "kessan",
  "tags": [
   "決算短信"
  ],
  "isCorrection": false,
  "market": "プライム"
 },
 {
  "id": "tdnet-1195818",
  "date": "2025-10-14",
  "time": "15:30",
  "code": "1419",
  "name": "タマホーム株式会社",
  "exch": "東",
  "title": "2026年５月期第１四半期 決算短信〔日本基準〕(連結)",
  "pdfUrl": "https://www.release.tdnet.info/inbs/140120251010571803.pdf",
  "src": "TDnet",
  "hasXbrl": true,
  "genre": "kessan",
  "tags": [
   "決算短信"
  ],
  "isCorrection": false,
  "market": "プライム"
 },
 {
  "id": "tdnet-1195815",
  "date": "2025-10-14",
  "time": "15:30",
  "code": "138A",
  "name": "光フードサービス株式会社",
  "exch": "東",
  "title": "2025年11月期 第３四半期決算短信〔日本基準〕（非連結）",
  "pdfUrl": "https://www.release.tdnet.info/inbs/140120251010571696.pdf",
  "src": "TDnet",
  "hasXbrl": true,
  "genre": "kessan",
  "tags": [
   "決算短信"
  ],
  "isCorrection": false,
  "market": "グロース"
 },
 {
  "id": "tdnet-1195808",
  "date": "2025-10-14",
  "time": "15:15",
  "code": "3065",
  "name": "株式会社ライフフーズ",
  "exch": "東",
  "title": "2026年２月期第２四半期（中間期）決算短信[日本基準]（非連結）",
  "pdfUrl": "https://www.release.tdnet.info/inbs/140120251009570922.pdf",
  "src": "TDnet",
  "hasXbrl": true,
  "genre": "kessan",
  "tags": [
   "決算短信"
  ],
  "isCorrection": false,
  "market": "スタンダード"
 },
 {
  "id": "tdnet-1195807",
  "date": "2025-10-14",
  "time": "15:00",
  "code": "9068",
  "name": "丸全昭和運輸株式会社",
  "exch": "東",
  "title": "日東富士運輸株式会社の株式の取得（子会社化）に関するお知らせ",
  "pdfUrl": "https://www.release.tdnet.info/inbs/140120251010571821.pdf",
  "src": "TDnet",
  "hasXbrl": false,
  "genre": "ma",
  "tags": [
   "子会社化"
  ],
  "isCorrection": false,
  "market": "プライム"
 },
 {
  "id": "tdnet-1195803",
  "date": "2025-10-14",
  "time": "15:00",
  "code": "8233",
  "name": "株式会社髙島屋",
  "exch": "東",
  "title": "2026年2月期 第2四半期（中間期）決算短信〔日本基準〕（連結）",
  "pdfUrl": "https://www.release.tdnet.info/inbs/140120251013572278.pdf",
  "src": "TDnet",
  "hasXbrl": true,
  "genre": "kessan",
  "tags": [
   "決算短信"
  ],
  "isCorrection": false,
  "market": "プライム"
 },
 {
  "id": "tdnet-1195797",
  "date": "2025-10-14",
  "time": "15:00",
  "code": "8198",
  "name": "マックスバリュ東海株式会社",
  "exch": "東",
  "title": "2026年２月期 第２四半期（中間期）決算短信〔日本基準〕（連結）",
  "pdfUrl": "https://www.release.tdnet.info/inbs/140120251013572268.pdf",
  "src": "TDnet",
  "hasXbrl": true,
  "genre": "kessan",
  "tags": [
   "決算短信"
  ],
  "isCorrection": false,
  "market": "スタンダード"
 },
 {
  "id": "tdnet-1195795",
  "date": "2025-10-14",
  "time": "15:00",
  "code": "8167",
  "name": "株式会社リテールパートナーズ",
  "exch": "東",
  "title": "2026年２月期　第２四半期（中間期）決算短信［日本基準］（連結）",
  "pdfUrl": "https://www.release.tdnet.info/inbs/140120251013572282.pdf",
  "src": "TDnet",
  "hasXbrl": true,
  "genre": "kessan",
  "tags": [
   "決算短信"
  ],
  "isCorrection": false,
  "market": "プライム"
 },
 {
  "id": "tdnet-1195794",
  "date": "2025-10-14",
  "time": "15:00",
  "code": "7847",
  "name": "株式会社グラファイトデザイン",
  "exch": "東",
  "title": "2026年２月期 第２四半期（中間期）決算短信〔日本基準〕（非連結）",
  "pdfUrl": "https://www.release.tdnet.info/inbs/140120251009570962.pdf",
  "src": "TDnet",
  "hasXbrl": true,
  "genre": "kessan",
  "tags": [
   "決算短信"
  ],
  "isCorrection": false,
  "market": "スタンダード"
 },
 {
  "id": "tdnet-1195792",
  "date": "2025-10-14",
  "time": "15:00",
  "code": "7520",
  "name": "株式会社エコス",
  "exch": "東",
  "title": "2026年2月期　第2四半期(中間期)決算短信[日本基準](連結)",
  "pdfUrl": "https://www.release.tdnet.info/inbs/140120251008570243.pdf",
  "src": "TDnet",
  "hasXbrl": true,
  "genre": "kessan",
  "tags": [
   "決算短信"
  ],
  "isCorrection": false,
  "market": "プライム"
 },
 {
  "id": "tdnet-1195791",
  "date": "2025-10-14",
  "time": "15:00",
  "code": "7450",
  "name": "サンデー",
  "exch": "東",
  "title": "2026年２月期 第２四半期（中間期）決算短信〔日本基準〕（非連結）",
  "pdfUrl": "https://www.release.tdnet.info/inbs/140120251014572422.pdf",
  "src": "TDnet",
  "hasXbrl": true,
  "genre": "kessan",
  "tags": [
   "決算短信"
  ],
  "isCorrection": false,
  "market": "不明"
 },
 {
  "id": "tdnet-1195788",
  "date": "2025-10-14",
  "time": "15:00",
  "code": "6142",
  "name": "富士精工株式会社",
  "exch": "名",
  "title": "2026年２月期 第２四半期（中間期）決算短信〔日本基準〕（連結）",
  "pdfUrl": "https://www.release.tdnet.info/inbs/140120251010572081.pdf",
  "src": "TDnet",
  "hasXbrl": true,
  "genre": "kessan",
  "tags": [
   "決算短信"
  ],
  "isCorrection": false,
  "market": "地方"
 },
 {
  "id": "tdnet-1195764",
  "date": "2025-10-14",
  "time": "14:30",
  "code": "2345",
  "name": "株式会社クシム",
  "exch": "東",
  "title": "株式会社Zaif株式譲渡の禁止に係る仮処分決定のお知らせ",
  "pdfUrl": "https://www.release.tdnet.info/inbs/140120251014572980.pdf",
  "src": "TDnet",
  "hasXbrl": false,
  "genre": "ma",
  "tags": [
   "株式譲渡"
  ],
  "isCorrection": false,
  "market": "スタンダード"
 },
 {
  "id": "tdnet-1195762",
  "date": "2025-10-14",
  "time": "14:00",
  "code": "5078",
  "name": "株式会社セレコーポレーション",
  "exch": "東",
  "title": "2026年２月期 第２四半期（中間期）決算短信〔日本基準〕(連結)",
  "pdfUrl": "https://www.release.tdnet.info/inbs/140120250902551933.pdf",
  "src": "TDnet",
  "hasXbrl": true,
  "genre": "kessan",
  "tags": [
   "決算短信"
  ],
  "isCorrection": false,
  "market": "スタンダード"
 },
 {
  "id": "tdnet-1195761",
  "date": "2025-10-14",
  "time": "14:00",
  "code": "4888",
  "name": "ステラファーマ株式会社",
  "exch": "東",
  "title": "通期業績予想及び中期経営計画の修正に関するお知らせ",
  "pdfUrl": "https://www.release.tdnet.info/inbs/140120251010571810.pdf",
  "src": "TDnet",
  "hasXbrl": true,
  "genre": "chukei",
  "tags": [
   "中期経営計画"
  ],
  "isCorrection": false,
  "market": "グロース"
 },
 {
  "id": "tdnet-1195757",
  "date": "2025-10-14",
  "time": "14:00",
  "code": "3536",
  "name": "アクサスホールディングス株式会社",
  "exch": "東",
  "title": "令和７年８月期 決算短信〔日本基準〕（連結）",
  "pdfUrl": "https://www.release.tdnet.info/inbs/140120251014572439.pdf",
  "src": "TDnet",
  "hasXbrl": true,
  "genre": "kessan",
  "tags": [
   "決算短信"
  ],
  "isCorrection": false,
  "market": "スタンダード"
 },
 {
  "id": "tdnet-1195754",
  "date": "2025-10-14",
  "time": "13:30",
  "code": "3177",
  "name": "株式会社ありがとうサービス",
  "exch": "東",
  "title": "2026年２月期 第２四半期(中間期)決算短信〔日本基準〕（連結）",
  "pdfUrl": "https://www.release.tdnet.info/inbs/140120250918559811.pdf",
  "src": "TDnet",
  "hasXbrl": true,
  "genre": "kessan",
  "tags": [
   "決算短信"
  ],
  "isCorrection": false,
  "market": "スタンダード"
 },
 {
  "id": "tdnet-1195752",
  "date": "2025-10-14",
  "time": "13:00",
  "code": "7434",
  "name": "株式会社オータケ",
  "exch": "東",
  "title": "2026年５月期 第１四半期決算短信〔日本基準〕（連結）",
  "pdfUrl": "https://www.release.tdnet.info/inbs/140120251007569640.pdf",
  "src": "TDnet",
  "hasXbrl": true,
  "genre": "kessan",
  "tags": [
   "決算短信"
  ],
  "isCorrection": false,
  "market": "スタンダード"
 },
 {
  "id": "tdnet-1195751",
  "date": "2025-10-14",
  "time": "13:00",
  "code": "3892",
  "name": "株式会社岡山製紙",
  "exch": "東",
  "title": "2026年５月期　第１四半期決算短信[日本基準](非連結)",
  "pdfUrl": "https://www.release.tdnet.info/inbs/140120251010572080.pdf",
  "src": "TDnet",
  "hasXbrl": true,
  "genre": "kessan",
  "tags": [
   "決算短信"
  ],
  "isCorrection": false,
  "market": "スタンダード"
 },
 {
  "id": "tdnet-1195746",
  "date": "2025-10-14",
  "time": "12:25",
  "code": "4440",
  "name": "株式会社ヴィッツ",
  "exch": "東",
  "title": "中期経営計画（2025年８月期～2027年８月期）の数値目標変更に関するお知らせ",
  "pdfUrl": "https://www.release.tdnet.info/inbs/140120251006569161.pdf",
  "src": "TDnet",
  "hasXbrl": false,
  "genre": "chukei",
  "tags": [
   "中期経営計画"
  ],
  "isCorrection": false,
  "market": "スタンダード"
 },
 {
  "id": "tdnet-1195745",
  "date": "2025-10-14",
  "time": "12:25",
  "code": "4440",
  "name": "株式会社ヴィッツ",
  "exch": "東",
  "title": "2025年８月期  決算短信〔日本基準〕（連結）",
  "pdfUrl": "https://www.release.tdnet.info/inbs/140120251009570632.pdf",
  "src": "TDnet",
  "hasXbrl": true,
  "genre": "kessan",
  "tags": [
   "決算短信"
  ],
  "isCorrection": false,
  "market": "スタンダード"
 },
 {
  "id": "tdnet-1195739",
  "date": "2025-10-14",
  "time": "12:00",
  "code": "7805",
  "name": "プリントネット株式会社",
  "exch": "東",
  "title": "2025年８月期 決算短信〔日本基準〕（非連結）",
  "pdfUrl": "https://www.release.tdnet.info/inbs/140120251014572557.pdf",
  "src": "TDnet",
  "hasXbrl": true,
  "genre": "kessan",
  "tags": [
   "決算短信"
  ],
  "isCorrection": false,
  "market": "スタンダード"
 },
 {
  "id": "tdnet-1195738",
  "date": "2025-10-14",
  "time": "12:00",
  "code": "7608",
  "name": "株式会社エスケイジャパン",
  "exch": "東",
  "title": "令和８年２月期 第２四半期（中間期）決算短信〔日本基準〕（連結）",
  "pdfUrl": "https://www.release.tdnet.info/inbs/140120251014572468.pdf",
  "src": "TDnet",
  "hasXbrl": true,
  "genre": "kessan",
  "tags": [
   "決算短信"
  ],
  "isCorrection": false,
  "market": "スタンダード"
 },
 {
  "id": "tdnet-1195735",
  "date": "2025-10-14",
  "time": "12:00",
  "code": "4735",
  "name": "株式会社京進",
  "exch": "東",
  "title": "株式会社リンクハートの株式の取得（子会社化）に関するお知らせ",
  "pdfUrl": "https://www.release.tdnet.info/inbs/140120251014572568.pdf",
  "src": "TDnet",
  "hasXbrl": false,
  "genre": "ma",
  "tags": [
   "子会社化"
  ],
  "isCorrection": false,
  "market": "スタンダード"
 },
 {
  "id": "tdnet-1195732",
  "date": "2025-10-14",
  "time": "12:00",
  "code": "3070",
  "name": "株式会社ジェリービーンズグループ",
  "exch": "東",
  "title": "補足資料  MAKE BEAUTURE 株式会社の株式取得(子会社化)に関する基本合意締結のお知らせ",
  "pdfUrl": "https://www.release.tdnet.info/inbs/140120251014572657.pdf",
  "src": "TDnet",
  "hasXbrl": false,
  "genre": "ma",
  "tags": [
   "株式取得",
   "子会社化"
  ],
  "isCorrection": false,
  "market": "グロース"
 },
 {
  "id": "tdnet-1195730",
  "date": "2025-10-14",
  "time": "12:00",
  "code": "209A",
  "name": "Ｐ－小野谷機工",
  "exch": "東",
  "title": "2025年８月期 決算短信〔日本基準〕（連結）",
  "pdfUrl": "https://www.release.tdnet.info/inbs/140120251010571578.pdf",
  "src": "TDnet",
  "hasXbrl": false,
  "genre": "kessan",
  "tags": [
   "決算短信"
  ],
  "isCorrection": false,
  "market": "不明"
 },
 {
  "id": "tdnet-1195727",
  "date": "2025-10-14",
  "time": "12:00",
  "code": "1430",
  "name": "ファーストコーポレーション株式会社",
  "exch": "東",
  "title": "2026年５月期 第１四半期決算短信〔日本基準〕(連結)",
  "pdfUrl": "https://www.release.tdnet.info/inbs/140120251014572384.pdf",
  "src": "TDnet",
  "hasXbrl": true,
  "genre": "kessan",
  "tags": [
   "決算短信"
  ],
  "isCorrection": false,
  "market": "スタンダード"
 },
 {
  "id": "tdnet-1195721",
  "date": "2025-10-14",
  "time": "11:30",
  "code": "190A",
  "name": "Ｃｈｏｒｄｉａ　Ｔｈｅｒａｐｅｕｔｉｃｓ株式会社",
  "exch": "東",
  "title": "2025年８月期  決算短信〔日本基準〕（非連結）",
  "pdfUrl": "https://www.release.tdnet.info/inbs/140120251014572406.pdf",
  "src": "TDnet",
  "hasXbrl": true,
  "genre": "kessan",
  "tags": [
   "決算短信"
  ],
  "isCorrection": false,
  "market": "グロース"
 },
 {
  "id": "tdnet-1195717",
  "date": "2025-10-14",
  "time": "10:30",
  "code": "3070",
  "name": "株式会社ジェリービーンズグループ",
  "exch": "東",
  "title": "（訂正）「MAKE BEAUTURE 株式会社の株式取得(子会社化)に関する基本合意締結のお知らせ」 の一部訂正について",
  "pdfUrl": "https://www.release.tdnet.info/inbs/140120251014572442.pdf",
  "src": "TDnet",
  "hasXbrl": false,
  "genre": "ma",
  "tags": [
   "株式取得",
   "子会社化"
  ],
  "isCorrection": true,
  "market": "グロース"
 },
 {
  "id": "tdnet-1195703",
  "date": "2025-10-14",
  "time": "08:30",
  "code": "2334",
  "name": "株式会社イオレ",
  "exch": "東",
  "title": "株式会社UPBONDとの業務提携に関するお知らせ",
  "pdfUrl": "https://www.release.tdnet.info/inbs/140120251014572347.pdf",
  "src": "TDnet",
  "hasXbrl": false,
  "genre": "release",
  "tags": [
   "業務提携"
  ],
  "isCorrection": false,
  "market": "グロース"
 }
]
